{"2,3": {"is_a_relation": 0, "num_tokens": 32, "same_sentence": 0, "target_before_source": 0, "intro_or_conc": 0, "num_between": 0, "num_in_paragraph": 3, "share_noun": 0, "num_shared_nouns": 0, "first_or_last": 1, "component_forward_indicators": 0, "context_forward_indicators": 0, "component_backwards_indicators": 0, "context_backwards_indicators": 0, "component_thesis_indicators": 0, "context_thesis_indicators": 0, "component_rebuttal_indicators": 0, "context_rebuttal_indicators": 0, "CC": 5, "CD": 0, "DT": 0, "EX": 0, "FW": 0, "IN": 2, "JJ": 1, "JJR": 0, "JJS": 0, "LS": 0, "MD": 0, "NN": 9, "NNS": 6, "NNP": 0, "NNPS": 0, "PDT": 0, "POS": 1, "PRP": 0, "PRP$": 1, "RB": 0, "RBR": 2, "RBS": 0, "RP": 0, "SYM": 0, "TO": 1, "UH": 0, "VB": 1, "VBD": 0, "VBG": 1, "VBN": 0, "VBP": 2, "VBZ": 0, "WDT": 0, "WP": 0, "WP$": 0, "WRB": 0, "['PP', ['IN', 'NP']]": 0, "['S', ['NP', 'VP']]": 0, "['ROOT', ['S']]": 1, "['NP', ['NP', 'PP']]": 0, "['ADVP', ['RB']]": 0, "['NP', ['DT', 'NN']]": 0, "['NP', ['NNS']]": 0, "['S', ['VP']]": 0, "['VP', ['TO', 'VP']]": 0, "['SBAR', ['IN', 'S']]": 0, "['NP', ['NN']]": 0, "['NP', ['JJ', 'NNS']]": 0, "['VP', ['VB', 'NP']]": 0, "['NP', ['NN', 'NN']]": 0, "['VP', ['VBZ', 'SBAR']]": 0, "['NP', ['PRP']]": 0, "['S', ['NP', 'VP', '.']]": 1, "['NP', ['NP', 'CC', 'NP']]": 0, "['VP', ['VBZ', 'NP']]": 0, "['NP', ['PRP$', 'NN']]": 0, "['NP', ['NML', 'NN']]": 0, "['ADJP', ['RB', 'JJ']]": 0, "['VP', ['VBP', 'PP', 'SBAR']]": 0, "['NP', ['NN', 'NNS']]": 0, "['VP', ['VP', 'CC', 'VP']]": 0, "['VP', ['VB', 'NP', 'PP']]": 0, "['NP', ['NN', 'CC', 'NN']]": 0, "['VP', ['VBP', 'VP']]": 0, "['VP', ['VBP', 'NP']]": 0, "['NP', ['NP', 'SBAR']]": 0, "['WHNP', ['WDT']]": 0, "['NP', ['ADJP', 'NN']]": 0, "['S', ['S', ',', 'CC', 'S', '.']]": 0, "['NP', ['DT', 'JJ', 'CD']]": 0, "['S', ['PP', 'NP', 'VP']]": 0, "['NP', ['DT', 'NML', 'NN']]": 0, "['NML', ['ADVP']]": 0, "['ADVP', ['RBR']]": 0, "['S', ['NP', 'PP']]": 0, "['NP', ['NP', 'ADJP']]": 0, "['NML', ['JJ', 'NNS']]": 0, "['NP', ['CD', 'NN']]": 0, "['NP', ['NN', 'CC', 'NNS']]": 0, "['NP', ['NP', 'NNS']]": 0, "['NP', ['JJ', 'NNS', 'POS']]": 0, "['SBAR', ['IN', 'NN', 'S']]": 0, "['NP', ['PRP$', 'NN', 'CC', 'NN']]": 0, "['NML', ['NN', 'NN', 'CC', 'NN']]": 0, "['VP', ['VBP', 'ADVP', 'VP']]": 0, "['ADVP', ['RBR', 'CC', 'RBR']]": 0, "['VP', ['VBG', 'NP']]": 0, "['NP', ['NNS', 'NNS']]": 0, "['S', ['S', 'CC', 'S', 'CC', 'S', '.']]": 0, "['S', ['NP', ',', 'NP', 'VP']]": 0, "['VP', ['MD', 'VP']]": 0, "['VP', ['VB', 'ADVP']]": 0, "['NP', ['RB']]": 0, "['S', ['ADVP', 'NP', 'VP']]": 0, "['VP', ['VBP', 'RB', 'VP']]": 0, "['VP', ['VB', 'NP', 'S']]": 0, "['NP', ['DT', 'JJR']]": 0, "['VP', ['VBZ', 'S']]": 0, "['SBAR', ['WHADVP', 'S']]": 0, "['WHADVP', ['WRB']]": 0, "['NP', ['DT', 'ADJP', 'NN']]": 0, "['ADJP', ['RBS', 'JJ']]": 0, "['S', ['ADVP', ',', 'NP', 'ADVP', 'VP', '.']]": 0, "['NP', ['JJ', 'NN']]": 0, "['VP', ['VB', 'NP', 'ADVP', 'S', 'SBAR']]": 0, "['VP', ['VBG', 'CC', 'VBG']]": 0, "['S', ['S', ':', 'S', '.']]": 0, "['S', ['NP', 'ADVP', 'VP']]": 0, "['NP', ['DT']]": 0, "['VP', ['VBP', 'NP', 'NP']]": 0, "['NP', ['NNS', 'CC', 'NNS']]": 0, "['S', ['ADVP', ',', 'NP', 'VP', '.']]": 0, "['NP', ['EX']]": 0, "['NP', ['NP', ',', 'NP']]": 0, "['SBAR', ['WHPP', 'S']]": 0, "['WHPP', ['IN', 'WHNP']]": 0, "['VP', ['VBN', 'PP', ',', 'PP']]": 0, "['NP', ['JJ', 'NNS', 'CC', 'NNS']]": 0, "['NP', ['``', 'NNP', 'NNP', \"''\"]]": 0, "['S', ['S', ',', 'NP', 'VP', '.']]": 0, "['VP', ['VB', 'PRT']]": 0, "['PRT', ['RP']]": 0, "['VP', ['VBZ', 'ADJP', 'SBAR']]": 0, "['ADJP', ['JJ']]": 0, "['NP', ['NP', ',', 'NP', 'CC', 'NP']]": 0, "['VP', ['VBP', 'NP', 'PP']]": 0, "['NP', ['NP', 'JJ', 'NNS']]": 0, "['NP', ['NNS', 'POS']]": 0, "['NP', ['NP', 'VP']]": 0, "['NP', ['PDT', 'DT', 'NNS']]": 0, "['VP', ['VBN', 'ADVP', ',', 'ADVP', 'S']]": 0, "['ADJP', ['JJ', 'CC', 'JJ']]": 0, "['SBAR', ['WHNP', 'S']]": 0, "['VP', ['VBP', 'PP']]": 0, "Comparison_Arg1_Explicit": 0, "Comparison_Arg1_Implicit": 0, "Comparison_Arg2_Explicit": 0, "Comparison_Arg2_Implicit": 0, "Contingency_Arg1_Explicit": 0, "Contingency_Arg1_Implicit": 1, "Contingency_Arg2_Explicit": 0, "Contingency_Arg2_Implicit": 0, "Expansion_Arg1_Explicit": 0, "Expansion_Arg1_Implicit": 1, "Expansion_Arg2_Explicit": 0, "Expansion_Arg2_Implicit": 2, "Temporal_Arg1_Explicit": 0, "Temporal_Arg1_Implicit": 0, "Temporal_Arg2_Explicit": 0, "Temporal_Arg2_Implicit": 0, "presence_positive_associations": 1, "presence_negative_associations": 1, "ratio_positive_associations": 0.71875, "ratio_negative_associations": 0.0625, "between_forward_indicators": 0, "between_backwards_indicators": 0, "between_thesis_indicators": 0, "between_rebuttal_indicators": 0}, "2,4": {"is_a_relation": 0, "num_tokens": 58, "same_sentence": 0, "target_before_source": 0, "intro_or_conc": 0, "num_between": 1, "num_in_paragraph": 3, "share_noun": 1, "num_shared_nouns": 1, "first_or_last": 1, "component_forward_indicators": 1, "context_forward_indicators": 1, "component_backwards_indicators": 0, "context_backwards_indicators": 0, "component_thesis_indicators": 0, "context_thesis_indicators": 0, "component_rebuttal_indicators": 1, "context_rebuttal_indicators": 0, "CC": 5, "CD": 0, "DT": 3, "EX": 0, "FW": 0, "IN": 6, "JJ": 4, "JJR": 1, "JJS": 0, "LS": 0, "MD": 1, "NN": 12, "NNS": 6, "NNP": 0, "NNPS": 0, "PDT": 0, "POS": 1, "PRP": 1, "PRP$": 2, "RB": 3, "RBR": 0, "RBS": 0, "RP": 0, "SYM": 0, "TO": 3, "UH": 0, "VB": 6, "VBD": 0, "VBG": 0, "VBN": 0, "VBP": 2, "VBZ": 1, "WDT": 0, "WP": 0, "WP$": 0, "WRB": 0, "['PP', ['IN', 'NP']]": 1, "['S', ['NP', 'VP']]": 1, "['ROOT', ['S']]": 1, "['NP', ['NP', 'PP']]": 0, "['ADVP', ['RB']]": 0, "['NP', ['DT', 'NN']]": 0, "['NP', ['NNS']]": 0, "['S', ['VP']]": 1, "['VP', ['TO', 'VP']]": 1, "['SBAR', ['IN', 'S']]": 0, "['NP', ['NN']]": 0, "['NP', ['JJ', 'NNS']]": 0, "['VP', ['VB', 'NP']]": 1, "['NP', ['NN', 'NN']]": 0, "['VP', ['VBZ', 'SBAR']]": 0, "['NP', ['PRP']]": 0, "['S', ['NP', 'VP', '.']]": 0, "['NP', ['NP', 'CC', 'NP']]": 0, "['VP', ['VBZ', 'NP']]": 0, "['NP', ['PRP$', 'NN']]": 0, "['NP', ['NML', 'NN']]": 0, "['ADJP', ['RB', 'JJ']]": 0, "['VP', ['VBP', 'PP', 'SBAR']]": 0, "['NP', ['NN', 'NNS']]": 0, "['VP', ['VP', 'CC', 'VP']]": 0, "['VP', ['VB', 'NP', 'PP']]": 0, "['NP', ['NN', 'CC', 'NN']]": 0, "['VP', ['VBP', 'VP']]": 0, "['VP', ['VBP', 'NP']]": 0, "['NP', ['NP', 'SBAR']]": 0, "['WHNP', ['WDT']]": 0, "['NP', ['ADJP', 'NN']]": 0, "['S', ['S', ',', 'CC', 'S', '.']]": 0, "['NP', ['DT', 'JJ', 'CD']]": 0, "['S', ['PP', 'NP', 'VP']]": 0, "['NP', ['DT', 'NML', 'NN']]": 0, "['NML', ['ADVP']]": 0, "['ADVP', ['RBR']]": 0, "['S', ['NP', 'PP']]": 0, "['NP', ['NP', 'ADJP']]": 0, "['NML', ['JJ', 'NNS']]": 0, "['NP', ['CD', 'NN']]": 0, "['NP', ['NN', 'CC', 'NNS']]": 0, "['NP', ['NP', 'NNS']]": 0, "['NP', ['JJ', 'NNS', 'POS']]": 0, "['SBAR', ['IN', 'NN', 'S']]": 0, "['NP', ['PRP$', 'NN', 'CC', 'NN']]": 0, "['NML', ['NN', 'NN', 'CC', 'NN']]": 0, "['VP', ['VBP', 'ADVP', 'VP']]": 0, "['ADVP', ['RBR', 'CC', 'RBR']]": 0, "['VP', ['VBG', 'NP']]": 0, "['NP', ['NNS', 'NNS']]": 0, "['S', ['S', 'CC', 'S', 'CC', 'S', '.']]": 0, "['S', ['NP', ',', 'NP', 'VP']]": 0, "['VP', ['MD', 'VP']]": 0, "['VP', ['VB', 'ADVP']]": 0, "['NP', ['RB']]": 0, "['S', ['ADVP', 'NP', 'VP']]": 0, "['VP', ['VBP', 'RB', 'VP']]": 0, "['VP', ['VB', 'NP', 'S']]": 0, "['NP', ['DT', 'JJR']]": 0, "['VP', ['VBZ', 'S']]": 0, "['SBAR', ['WHADVP', 'S']]": 0, "['WHADVP', ['WRB']]": 0, "['NP', ['DT', 'ADJP', 'NN']]": 0, "['ADJP', ['RBS', 'JJ']]": 0, "['S', ['ADVP', ',', 'NP', 'ADVP', 'VP', '.']]": 0, "['NP', ['JJ', 'NN']]": 0, "['VP', ['VB', 'NP', 'ADVP', 'S', 'SBAR']]": 0, "['VP', ['VBG', 'CC', 'VBG']]": 0, "['S', ['S', ':', 'S', '.']]": 0, "['S', ['NP', 'ADVP', 'VP']]": 0, "['NP', ['DT']]": 0, "['VP', ['VBP', 'NP', 'NP']]": 0, "['NP', ['NNS', 'CC', 'NNS']]": 0, "['S', ['ADVP', ',', 'NP', 'VP', '.']]": 0, "['NP', ['EX']]": 0, "['NP', ['NP', ',', 'NP']]": 0, "['SBAR', ['WHPP', 'S']]": 0, "['WHPP', ['IN', 'WHNP']]": 0, "['VP', ['VBN', 'PP', ',', 'PP']]": 0, "['NP', ['JJ', 'NNS', 'CC', 'NNS']]": 0, "['NP', ['``', 'NNP', 'NNP', \"''\"]]": 0, "['S', ['S', ',', 'NP', 'VP', '.']]": 0, "['VP', ['VB', 'PRT']]": 0, "['PRT', ['RP']]": 0, "['VP', ['VBZ', 'ADJP', 'SBAR']]": 0, "['ADJP', ['JJ']]": 0, "['NP', ['NP', ',', 'NP', 'CC', 'NP']]": 0, "['VP', ['VBP', 'NP', 'PP']]": 0, "['NP', ['NP', 'JJ', 'NNS']]": 0, "['NP', ['NNS', 'POS']]": 0, "['NP', ['NP', 'VP']]": 0, "['NP', ['PDT', 'DT', 'NNS']]": 0, "['VP', ['VBN', 'ADVP', ',', 'ADVP', 'S']]": 0, "['ADJP', ['JJ', 'CC', 'JJ']]": 0, "['SBAR', ['WHNP', 'S']]": 0, "['VP', ['VBP', 'PP']]": 0, "Comparison_Arg1_Explicit": 1, "Comparison_Arg1_Implicit": 0, "Comparison_Arg2_Explicit": 0, "Comparison_Arg2_Implicit": 0, "Contingency_Arg1_Explicit": 0, "Contingency_Arg1_Implicit": 1, "Contingency_Arg2_Explicit": 0, "Contingency_Arg2_Implicit": 1, "Expansion_Arg1_Explicit": 0, "Expansion_Arg1_Implicit": 1, "Expansion_Arg2_Explicit": 0, "Expansion_Arg2_Implicit": 1, "Temporal_Arg1_Explicit": 0, "Temporal_Arg1_Implicit": 0, "Temporal_Arg2_Explicit": 0, "Temporal_Arg2_Implicit": 0, "presence_positive_associations": 1, "presence_negative_associations": 1, "ratio_positive_associations": 0.39655172413793105, "ratio_negative_associations": 0.034482758620689655, "between_forward_indicators": 0, "between_backwards_indicators": 0, "between_thesis_indicators": 0, "between_rebuttal_indicators": 0}, "3,2": {"is_a_relation": 1, "num_tokens": 32, "same_sentence": 0, "target_before_source": 1, "intro_or_conc": 0, "num_between": 0, "num_in_paragraph": 3, "share_noun": 0, "num_shared_nouns": 0, "first_or_last": 1, "component_forward_indicators": 0, "context_forward_indicators": 0, "component_backwards_indicators": 0, "context_backwards_indicators": 0, "component_thesis_indicators": 0, "context_thesis_indicators": 0, "component_rebuttal_indicators": 0, "context_rebuttal_indicators": 0, "CC": 5, "CD": 0, "DT": 0, "EX": 0, "FW": 0, "IN": 2, "JJ": 1, "JJR": 0, "JJS": 0, "LS": 0, "MD": 0, "NN": 9, "NNS": 6, "NNP": 0, "NNPS": 0, "PDT": 0, "POS": 1, "PRP": 0, "PRP$": 1, "RB": 0, "RBR": 2, "RBS": 0, "RP": 0, "SYM": 0, "TO": 1, "UH": 0, "VB": 1, "VBD": 0, "VBG": 1, "VBN": 0, "VBP": 2, "VBZ": 0, "WDT": 0, "WP": 0, "WP$": 0, "WRB": 0, "['PP', ['IN', 'NP']]": 0, "['S', ['NP', 'VP']]": 0, "['ROOT', ['S']]": 1, "['NP', ['NP', 'PP']]": 0, "['ADVP', ['RB']]": 0, "['NP', ['DT', 'NN']]": 0, "['NP', ['NNS']]": 0, "['S', ['VP']]": 0, "['VP', ['TO', 'VP']]": 0, "['SBAR', ['IN', 'S']]": 0, "['NP', ['NN']]": 0, "['NP', ['JJ', 'NNS']]": 0, "['VP', ['VB', 'NP']]": 0, "['NP', ['NN', 'NN']]": 0, "['VP', ['VBZ', 'SBAR']]": 0, "['NP', ['PRP']]": 0, "['S', ['NP', 'VP', '.']]": 1, "['NP', ['NP', 'CC', 'NP']]": 0, "['VP', ['VBZ', 'NP']]": 0, "['NP', ['PRP$', 'NN']]": 0, "['NP', ['NML', 'NN']]": 0, "['ADJP', ['RB', 'JJ']]": 0, "['VP', ['VBP', 'PP', 'SBAR']]": 0, "['NP', ['NN', 'NNS']]": 0, "['VP', ['VP', 'CC', 'VP']]": 0, "['VP', ['VB', 'NP', 'PP']]": 0, "['NP', ['NN', 'CC', 'NN']]": 0, "['VP', ['VBP', 'VP']]": 0, "['VP', ['VBP', 'NP']]": 0, "['NP', ['NP', 'SBAR']]": 0, "['WHNP', ['WDT']]": 0, "['NP', ['ADJP', 'NN']]": 0, "['S', ['S', ',', 'CC', 'S', '.']]": 0, "['NP', ['DT', 'JJ', 'CD']]": 0, "['S', ['PP', 'NP', 'VP']]": 0, "['NP', ['DT', 'NML', 'NN']]": 0, "['NML', ['ADVP']]": 0, "['ADVP', ['RBR']]": 0, "['S', ['NP', 'PP']]": 0, "['NP', ['NP', 'ADJP']]": 0, "['NML', ['JJ', 'NNS']]": 0, "['NP', ['CD', 'NN']]": 0, "['NP', ['NN', 'CC', 'NNS']]": 0, "['NP', ['NP', 'NNS']]": 0, "['NP', ['JJ', 'NNS', 'POS']]": 0, "['SBAR', ['IN', 'NN', 'S']]": 0, "['NP', ['PRP$', 'NN', 'CC', 'NN']]": 0, "['NML', ['NN', 'NN', 'CC', 'NN']]": 0, "['VP', ['VBP', 'ADVP', 'VP']]": 0, "['ADVP', ['RBR', 'CC', 'RBR']]": 0, "['VP', ['VBG', 'NP']]": 0, "['NP', ['NNS', 'NNS']]": 0, "['S', ['S', 'CC', 'S', 'CC', 'S', '.']]": 0, "['S', ['NP', ',', 'NP', 'VP']]": 0, "['VP', ['MD', 'VP']]": 0, "['VP', ['VB', 'ADVP']]": 0, "['NP', ['RB']]": 0, "['S', ['ADVP', 'NP', 'VP']]": 0, "['VP', ['VBP', 'RB', 'VP']]": 0, "['VP', ['VB', 'NP', 'S']]": 0, "['NP', ['DT', 'JJR']]": 0, "['VP', ['VBZ', 'S']]": 0, "['SBAR', ['WHADVP', 'S']]": 0, "['WHADVP', ['WRB']]": 0, "['NP', ['DT', 'ADJP', 'NN']]": 0, "['ADJP', ['RBS', 'JJ']]": 0, "['S', ['ADVP', ',', 'NP', 'ADVP', 'VP', '.']]": 0, "['NP', ['JJ', 'NN']]": 0, "['VP', ['VB', 'NP', 'ADVP', 'S', 'SBAR']]": 0, "['VP', ['VBG', 'CC', 'VBG']]": 0, "['S', ['S', ':', 'S', '.']]": 0, "['S', ['NP', 'ADVP', 'VP']]": 0, "['NP', ['DT']]": 0, "['VP', ['VBP', 'NP', 'NP']]": 0, "['NP', ['NNS', 'CC', 'NNS']]": 0, "['S', ['ADVP', ',', 'NP', 'VP', '.']]": 0, "['NP', ['EX']]": 0, "['NP', ['NP', ',', 'NP']]": 0, "['SBAR', ['WHPP', 'S']]": 0, "['WHPP', ['IN', 'WHNP']]": 0, "['VP', ['VBN', 'PP', ',', 'PP']]": 0, "['NP', ['JJ', 'NNS', 'CC', 'NNS']]": 0, "['NP', ['``', 'NNP', 'NNP', \"''\"]]": 0, "['S', ['S', ',', 'NP', 'VP', '.']]": 0, "['VP', ['VB', 'PRT']]": 0, "['PRT', ['RP']]": 0, "['VP', ['VBZ', 'ADJP', 'SBAR']]": 0, "['ADJP', ['JJ']]": 0, "['NP', ['NP', ',', 'NP', 'CC', 'NP']]": 0, "['VP', ['VBP', 'NP', 'PP']]": 0, "['NP', ['NP', 'JJ', 'NNS']]": 0, "['NP', ['NNS', 'POS']]": 0, "['NP', ['NP', 'VP']]": 0, "['NP', ['PDT', 'DT', 'NNS']]": 0, "['VP', ['VBN', 'ADVP', ',', 'ADVP', 'S']]": 0, "['ADJP', ['JJ', 'CC', 'JJ']]": 0, "['SBAR', ['WHNP', 'S']]": 0, "['VP', ['VBP', 'PP']]": 0, "Comparison_Arg1_Explicit": 0, "Comparison_Arg1_Implicit": 0, "Comparison_Arg2_Explicit": 0, "Comparison_Arg2_Implicit": 0, "Contingency_Arg1_Explicit": 0, "Contingency_Arg1_Implicit": 1, "Contingency_Arg2_Explicit": 0, "Contingency_Arg2_Implicit": 0, "Expansion_Arg1_Explicit": 0, "Expansion_Arg1_Implicit": 1, "Expansion_Arg2_Explicit": 0, "Expansion_Arg2_Implicit": 2, "Temporal_Arg1_Explicit": 0, "Temporal_Arg1_Implicit": 0, "Temporal_Arg2_Explicit": 0, "Temporal_Arg2_Implicit": 0, "presence_positive_associations": 1, "presence_negative_associations": 0, "ratio_positive_associations": 0.59375, "ratio_negative_associations": 0.0, "between_forward_indicators": 0, "between_backwards_indicators": 0, "between_thesis_indicators": 0, "between_rebuttal_indicators": 0}, "3,4": {"is_a_relation": 0, "num_tokens": 56, "same_sentence": 0, "target_before_source": 0, "intro_or_conc": 0, "num_between": 0, "num_in_paragraph": 3, "share_noun": 1, "num_shared_nouns": 1, "first_or_last": 1, "component_forward_indicators": 1, "context_forward_indicators": 1, "component_backwards_indicators": 0, "context_backwards_indicators": 0, "component_thesis_indicators": 0, "context_thesis_indicators": 0, "component_rebuttal_indicators": 1, "context_rebuttal_indicators": 0, "CC": 6, "CD": 0, "DT": 3, "EX": 0, "FW": 0, "IN": 4, "JJ": 3, "JJR": 1, "JJS": 0, "LS": 0, "MD": 1, "NN": 13, "NNS": 6, "NNP": 0, "NNPS": 0, "PDT": 0, "POS": 0, "PRP": 1, "PRP$": 1, "RB": 3, "RBR": 2, "RBS": 0, "RP": 0, "SYM": 0, "TO": 2, "UH": 0, "VB": 5, "VBD": 0, "VBG": 1, "VBN": 0, "VBP": 2, "VBZ": 1, "WDT": 0, "WP": 0, "WP$": 0, "WRB": 0, "['PP', ['IN', 'NP']]": 0, "['S', ['NP', 'VP']]": 0, "['ROOT', ['S']]": 1, "['NP', ['NP', 'PP']]": 0, "['ADVP', ['RB']]": 0, "['NP', ['DT', 'NN']]": 0, "['NP', ['NNS']]": 0, "['S', ['VP']]": 0, "['VP', ['TO', 'VP']]": 0, "['SBAR', ['IN', 'S']]": 0, "['NP', ['NN']]": 0, "['NP', ['JJ', 'NNS']]": 0, "['VP', ['VB', 'NP']]": 0, "['NP', ['NN', 'NN']]": 0, "['VP', ['VBZ', 'SBAR']]": 0, "['NP', ['PRP']]": 0, "['S', ['NP', 'VP', '.']]": 0, "['NP', ['NP', 'CC', 'NP']]": 1, "['VP', ['VBZ', 'NP']]": 0, "['NP', ['PRP$', 'NN']]": 0, "['NP', ['NML', 'NN']]": 0, "['ADJP', ['RB', 'JJ']]": 0, "['VP', ['VBP', 'PP', 'SBAR']]": 0, "['NP', ['NN', 'NNS']]": 0, "['VP', ['VP', 'CC', 'VP']]": 0, "['VP', ['VB', 'NP', 'PP']]": 0, "['NP', ['NN', 'CC', 'NN']]": 0, "['VP', ['VBP', 'VP']]": 0, "['VP', ['VBP', 'NP']]": 0, "['NP', ['NP', 'SBAR']]": 0, "['WHNP', ['WDT']]": 0, "['NP', ['ADJP', 'NN']]": 0, "['S', ['S', ',', 'CC', 'S', '.']]": 0, "['NP', ['DT', 'JJ', 'CD']]": 0, "['S', ['PP', 'NP', 'VP']]": 0, "['NP', ['DT', 'NML', 'NN']]": 0, "['NML', ['ADVP']]": 0, "['ADVP', ['RBR']]": 0, "['S', ['NP', 'PP']]": 0, "['NP', ['NP', 'ADJP']]": 0, "['NML', ['JJ', 'NNS']]": 0, "['NP', ['CD', 'NN']]": 0, "['NP', ['NN', 'CC', 'NNS']]": 0, "['NP', ['NP', 'NNS']]": 0, "['NP', ['JJ', 'NNS', 'POS']]": 0, "['SBAR', ['IN', 'NN', 'S']]": 0, "['NP', ['PRP$', 'NN', 'CC', 'NN']]": 0, "['NML', ['NN', 'NN', 'CC', 'NN']]": 0, "['VP', ['VBP', 'ADVP', 'VP']]": 0, "['ADVP', ['RBR', 'CC', 'RBR']]": 0, "['VP', ['VBG', 'NP']]": 0, "['NP', ['NNS', 'NNS']]": 0, "['S', ['S', 'CC', 'S', 'CC', 'S', '.']]": 0, "['S', ['NP', ',', 'NP', 'VP']]": 0, "['VP', ['MD', 'VP']]": 0, "['VP', ['VB', 'ADVP']]": 0, "['NP', ['RB']]": 0, "['S', ['ADVP', 'NP', 'VP']]": 0, "['VP', ['VBP', 'RB', 'VP']]": 0, "['VP', ['VB', 'NP', 'S']]": 0, "['NP', ['DT', 'JJR']]": 0, "['VP', ['VBZ', 'S']]": 0, "['SBAR', ['WHADVP', 'S']]": 0, "['WHADVP', ['WRB']]": 0, "['NP', ['DT', 'ADJP', 'NN']]": 0, "['ADJP', ['RBS', 'JJ']]": 0, "['S', ['ADVP', ',', 'NP', 'ADVP', 'VP', '.']]": 0, "['NP', ['JJ', 'NN']]": 0, "['VP', ['VB', 'NP', 'ADVP', 'S', 'SBAR']]": 0, "['VP', ['VBG', 'CC', 'VBG']]": 0, "['S', ['S', ':', 'S', '.']]": 0, "['S', ['NP', 'ADVP', 'VP']]": 0, "['NP', ['DT']]": 0, "['VP', ['VBP', 'NP', 'NP']]": 0, "['NP', ['NNS', 'CC', 'NNS']]": 0, "['S', ['ADVP', ',', 'NP', 'VP', '.']]": 0, "['NP', ['EX']]": 0, "['NP', ['NP', ',', 'NP']]": 0, "['SBAR', ['WHPP', 'S']]": 0, "['WHPP', ['IN', 'WHNP']]": 0, "['VP', ['VBN', 'PP', ',', 'PP']]": 0, "['NP', ['JJ', 'NNS', 'CC', 'NNS']]": 0, "['NP', ['``', 'NNP', 'NNP', \"''\"]]": 0, "['S', ['S', ',', 'NP', 'VP', '.']]": 0, "['VP', ['VB', 'PRT']]": 0, "['PRT', ['RP']]": 0, "['VP', ['VBZ', 'ADJP', 'SBAR']]": 0, "['ADJP', ['JJ']]": 0, "['NP', ['NP', ',', 'NP', 'CC', 'NP']]": 0, "['VP', ['VBP', 'NP', 'PP']]": 0, "['NP', ['NP', 'JJ', 'NNS']]": 0, "['NP', ['NNS', 'POS']]": 0, "['NP', ['NP', 'VP']]": 0, "['NP', ['PDT', 'DT', 'NNS']]": 0, "['VP', ['VBN', 'ADVP', ',', 'ADVP', 'S']]": 0, "['ADJP', ['JJ', 'CC', 'JJ']]": 0, "['SBAR', ['WHNP', 'S']]": 0, "['VP', ['VBP', 'PP']]": 0, "Comparison_Arg1_Explicit": 1, "Comparison_Arg1_Implicit": 0, "Comparison_Arg2_Explicit": 0, "Comparison_Arg2_Implicit": 0, "Contingency_Arg1_Explicit": 0, "Contingency_Arg1_Implicit": 2, "Contingency_Arg2_Explicit": 0, "Contingency_Arg2_Implicit": 1, "Expansion_Arg1_Explicit": 0, "Expansion_Arg1_Implicit": 0, "Expansion_Arg2_Explicit": 0, "Expansion_Arg2_Implicit": 1, "Temporal_Arg1_Explicit": 0, "Temporal_Arg1_Implicit": 0, "Temporal_Arg2_Explicit": 0, "Temporal_Arg2_Implicit": 0, "presence_positive_associations": 1, "presence_negative_associations": 0, "ratio_positive_associations": 0.3392857142857143, "ratio_negative_associations": 0.0, "between_forward_indicators": 0, "between_backwards_indicators": 0, "between_thesis_indicators": 0, "between_rebuttal_indicators": 0}, "4,2": {"is_a_relation": 0, "num_tokens": 58, "same_sentence": 0, "target_before_source": 1, "intro_or_conc": 0, "num_between": 1, "num_in_paragraph": 3, "share_noun": 1, "num_shared_nouns": 1, "first_or_last": 1, "component_forward_indicators": 1, "context_forward_indicators": 1, "component_backwards_indicators": 0, "context_backwards_indicators": 0, "component_thesis_indicators": 0, "context_thesis_indicators": 0, "component_rebuttal_indicators": 1, "context_rebuttal_indicators": 0, "CC": 5, "CD": 0, "DT": 3, "EX": 0, "FW": 0, "IN": 6, "JJ": 4, "JJR": 1, "JJS": 0, "LS": 0, "MD": 1, "NN": 12, "NNS": 6, "NNP": 0, "NNPS": 0, "PDT": 0, "POS": 1, "PRP": 1, "PRP$": 2, "RB": 3, "RBR": 0, "RBS": 0, "RP": 0, "SYM": 0, "TO": 3, "UH": 0, "VB": 6, "VBD": 0, "VBG": 0, "VBN": 0, "VBP": 2, "VBZ": 1, "WDT": 0, "WP": 0, "WP$": 0, "WRB": 0, "['PP', ['IN', 'NP']]": 4, "['S', ['NP', 'VP']]": 1, "['ROOT', ['S']]": 1, "['NP', ['NP', 'PP']]": 0, "['ADVP', ['RB']]": 0, "['NP', ['DT', 'NN']]": 0, "['NP', ['NNS']]": 0, "['S', ['VP']]": 2, "['VP', ['TO', 'VP']]": 2, "['SBAR', ['IN', 'S']]": 0, "['NP', ['NN']]": 0, "['NP', ['JJ', 'NNS']]": 0, "['VP', ['VB', 'NP']]": 2, "['NP', ['NN', 'NN']]": 0, "['VP', ['VBZ', 'SBAR']]": 0, "['NP', ['PRP']]": 0, "['S', ['NP', 'VP', '.']]": 0, "['NP', ['NP', 'CC', 'NP']]": 0, "['VP', ['VBZ', 'NP']]": 0, "['NP', ['PRP$', 'NN']]": 0, "['NP', ['NML', 'NN']]": 0, "['ADJP', ['RB', 'JJ']]": 0, "['VP', ['VBP', 'PP', 'SBAR']]": 0, "['NP', ['NN', 'NNS']]": 0, "['VP', ['VP', 'CC', 'VP']]": 0, "['VP', ['VB', 'NP', 'PP']]": 0, "['NP', ['NN', 'CC', 'NN']]": 0, "['VP', ['VBP', 'VP']]": 0, "['VP', ['VBP', 'NP']]": 0, "['NP', ['NP', 'SBAR']]": 0, "['WHNP', ['WDT']]": 0, "['NP', ['ADJP', 'NN']]": 0, "['S', ['S', ',', 'CC', 'S', '.']]": 0, "['NP', ['DT', 'JJ', 'CD']]": 0, "['S', ['PP', 'NP', 'VP']]": 0, "['NP', ['DT', 'NML', 'NN']]": 0, "['NML', ['ADVP']]": 0, "['ADVP', ['RBR']]": 0, "['S', ['NP', 'PP']]": 0, "['NP', ['NP', 'ADJP']]": 0, "['NML', ['JJ', 'NNS']]": 0, "['NP', ['CD', 'NN']]": 0, "['NP', ['NN', 'CC', 'NNS']]": 0, "['NP', ['NP', 'NNS']]": 0, "['NP', ['JJ', 'NNS', 'POS']]": 0, "['SBAR', ['IN', 'NN', 'S']]": 0, "['NP', ['PRP$', 'NN', 'CC', 'NN']]": 0, "['NML', ['NN', 'NN', 'CC', 'NN']]": 0, "['VP', ['VBP', 'ADVP', 'VP']]": 0, "['ADVP', ['RBR', 'CC', 'RBR']]": 0, "['VP', ['VBG', 'NP']]": 0, "['NP', ['NNS', 'NNS']]": 0, "['S', ['S', 'CC', 'S', 'CC', 'S', '.']]": 0, "['S', ['NP', ',', 'NP', 'VP']]": 0, "['VP', ['MD', 'VP']]": 0, "['VP', ['VB', 'ADVP']]": 0, "['NP', ['RB']]": 0, "['S', ['ADVP', 'NP', 'VP']]": 0, "['VP', ['VBP', 'RB', 'VP']]": 0, "['VP', ['VB', 'NP', 'S']]": 0, "['NP', ['DT', 'JJR']]": 0, "['VP', ['VBZ', 'S']]": 0, "['SBAR', ['WHADVP', 'S']]": 0, "['WHADVP', ['WRB']]": 0, "['NP', ['DT', 'ADJP', 'NN']]": 0, "['ADJP', ['RBS', 'JJ']]": 0, "['S', ['ADVP', ',', 'NP', 'ADVP', 'VP', '.']]": 0, "['NP', ['JJ', 'NN']]": 0, "['VP', ['VB', 'NP', 'ADVP', 'S', 'SBAR']]": 0, "['VP', ['VBG', 'CC', 'VBG']]": 0, "['S', ['S', ':', 'S', '.']]": 0, "['S', ['NP', 'ADVP', 'VP']]": 0, "['NP', ['DT']]": 0, "['VP', ['VBP', 'NP', 'NP']]": 0, "['NP', ['NNS', 'CC', 'NNS']]": 0, "['S', ['ADVP', ',', 'NP', 'VP', '.']]": 0, "['NP', ['EX']]": 0, "['NP', ['NP', ',', 'NP']]": 0, "['SBAR', ['WHPP', 'S']]": 0, "['WHPP', ['IN', 'WHNP']]": 0, "['VP', ['VBN', 'PP', ',', 'PP']]": 0, "['NP', ['JJ', 'NNS', 'CC', 'NNS']]": 0, "['NP', ['``', 'NNP', 'NNP', \"''\"]]": 0, "['S', ['S', ',', 'NP', 'VP', '.']]": 0, "['VP', ['VB', 'PRT']]": 0, "['PRT', ['RP']]": 0, "['VP', ['VBZ', 'ADJP', 'SBAR']]": 0, "['ADJP', ['JJ']]": 0, "['NP', ['NP', ',', 'NP', 'CC', 'NP']]": 0, "['VP', ['VBP', 'NP', 'PP']]": 0, "['NP', ['NP', 'JJ', 'NNS']]": 0, "['NP', ['NNS', 'POS']]": 0, "['NP', ['NP', 'VP']]": 0, "['NP', ['PDT', 'DT', 'NNS']]": 0, "['VP', ['VBN', 'ADVP', ',', 'ADVP', 'S']]": 0, "['ADJP', ['JJ', 'CC', 'JJ']]": 0, "['SBAR', ['WHNP', 'S']]": 0, "['VP', ['VBP', 'PP']]": 0, "Comparison_Arg1_Explicit": 1, "Comparison_Arg1_Implicit": 0, "Comparison_Arg2_Explicit": 0, "Comparison_Arg2_Implicit": 0, "Contingency_Arg1_Explicit": 0, "Contingency_Arg1_Implicit": 1, "Contingency_Arg2_Explicit": 0, "Contingency_Arg2_Implicit": 1, "Expansion_Arg1_Explicit": 0, "Expansion_Arg1_Implicit": 1, "Expansion_Arg2_Explicit": 0, "Expansion_Arg2_Implicit": 1, "Temporal_Arg1_Explicit": 0, "Temporal_Arg1_Implicit": 0, "Temporal_Arg2_Explicit": 0, "Temporal_Arg2_Implicit": 0, "presence_positive_associations": 1, "presence_negative_associations": 1, "ratio_positive_associations": 0.7586206896551724, "ratio_negative_associations": 0.15517241379310345, "between_forward_indicators": 0, "between_backwards_indicators": 0, "between_thesis_indicators": 0, "between_rebuttal_indicators": 0}, "4,3": {"is_a_relation": 0, "num_tokens": 56, "same_sentence": 0, "target_before_source": 1, "intro_or_conc": 0, "num_between": 0, "num_in_paragraph": 3, "share_noun": 1, "num_shared_nouns": 1, "first_or_last": 1, "component_forward_indicators": 1, "context_forward_indicators": 1, "component_backwards_indicators": 0, "context_backwards_indicators": 0, "component_thesis_indicators": 0, "context_thesis_indicators": 0, "component_rebuttal_indicators": 1, "context_rebuttal_indicators": 0, "CC": 6, "CD": 0, "DT": 3, "EX": 0, "FW": 0, "IN": 4, "JJ": 3, "JJR": 1, "JJS": 0, "LS": 0, "MD": 1, "NN": 13, "NNS": 6, "NNP": 0, "NNPS": 0, "PDT": 0, "POS": 0, "PRP": 1, "PRP$": 1, "RB": 3, "RBR": 2, "RBS": 0, "RP": 0, "SYM": 0, "TO": 2, "UH": 0, "VB": 5, "VBD": 0, "VBG": 1, "VBN": 0, "VBP": 2, "VBZ": 1, "WDT": 0, "WP": 0, "WP$": 0, "WRB": 0, "['PP', ['IN', 'NP']]": 0, "['S', ['NP', 'VP']]": 0, "['ROOT', ['S']]": 1, "['NP', ['NP', 'PP']]": 0, "['ADVP', ['RB']]": 0, "['NP', ['DT', 'NN']]": 0, "['NP', ['NNS']]": 0, "['S', ['VP']]": 0, "['VP', ['TO', 'VP']]": 0, "['SBAR', ['IN', 'S']]": 0, "['NP', ['NN']]": 0, "['NP', ['JJ', 'NNS']]": 0, "['VP', ['VB', 'NP']]": 0, "['NP', ['NN', 'NN']]": 0, "['VP', ['VBZ', 'SBAR']]": 0, "['NP', ['PRP']]": 0, "['S', ['NP', 'VP', '.']]": 0, "['NP', ['NP', 'CC', 'NP']]": 1, "['VP', ['VBZ', 'NP']]": 0, "['NP', ['PRP$', 'NN']]": 0, "['NP', ['NML', 'NN']]": 0, "['ADJP', ['RB', 'JJ']]": 0, "['VP', ['VBP', 'PP', 'SBAR']]": 0, "['NP', ['NN', 'NNS']]": 0, "['VP', ['VP', 'CC', 'VP']]": 0, "['VP', ['VB', 'NP', 'PP']]": 0, "['NP', ['NN', 'CC', 'NN']]": 0, "['VP', ['VBP', 'VP']]": 0, "['VP', ['VBP', 'NP']]": 0, "['NP', ['NP', 'SBAR']]": 0, "['WHNP', ['WDT']]": 0, "['NP', ['ADJP', 'NN']]": 0, "['S', ['S', ',', 'CC', 'S', '.']]": 0, "['NP', ['DT', 'JJ', 'CD']]": 0, "['S', ['PP', 'NP', 'VP']]": 0, "['NP', ['DT', 'NML', 'NN']]": 0, "['NML', ['ADVP']]": 0, "['ADVP', ['RBR']]": 0, "['S', ['NP', 'PP']]": 0, "['NP', ['NP', 'ADJP']]": 0, "['NML', ['JJ', 'NNS']]": 0, "['NP', ['CD', 'NN']]": 0, "['NP', ['NN', 'CC', 'NNS']]": 0, "['NP', ['NP', 'NNS']]": 0, "['NP', ['JJ', 'NNS', 'POS']]": 0, "['SBAR', ['IN', 'NN', 'S']]": 0, "['NP', ['PRP$', 'NN', 'CC', 'NN']]": 0, "['NML', ['NN', 'NN', 'CC', 'NN']]": 0, "['VP', ['VBP', 'ADVP', 'VP']]": 0, "['ADVP', ['RBR', 'CC', 'RBR']]": 0, "['VP', ['VBG', 'NP']]": 0, "['NP', ['NNS', 'NNS']]": 0, "['S', ['S', 'CC', 'S', 'CC', 'S', '.']]": 0, "['S', ['NP', ',', 'NP', 'VP']]": 0, "['VP', ['MD', 'VP']]": 0, "['VP', ['VB', 'ADVP']]": 0, "['NP', ['RB']]": 0, "['S', ['ADVP', 'NP', 'VP']]": 0, "['VP', ['VBP', 'RB', 'VP']]": 0, "['VP', ['VB', 'NP', 'S']]": 0, "['NP', ['DT', 'JJR']]": 0, "['VP', ['VBZ', 'S']]": 0, "['SBAR', ['WHADVP', 'S']]": 0, "['WHADVP', ['WRB']]": 0, "['NP', ['DT', 'ADJP', 'NN']]": 0, "['ADJP', ['RBS', 'JJ']]": 0, "['S', ['ADVP', ',', 'NP', 'ADVP', 'VP', '.']]": 0, "['NP', ['JJ', 'NN']]": 0, "['VP', ['VB', 'NP', 'ADVP', 'S', 'SBAR']]": 0, "['VP', ['VBG', 'CC', 'VBG']]": 0, "['S', ['S', ':', 'S', '.']]": 0, "['S', ['NP', 'ADVP', 'VP']]": 0, "['NP', ['DT']]": 0, "['VP', ['VBP', 'NP', 'NP']]": 0, "['NP', ['NNS', 'CC', 'NNS']]": 0, "['S', ['ADVP', ',', 'NP', 'VP', '.']]": 0, "['NP', ['EX']]": 0, "['NP', ['NP', ',', 'NP']]": 0, "['SBAR', ['WHPP', 'S']]": 0, "['WHPP', ['IN', 'WHNP']]": 0, "['VP', ['VBN', 'PP', ',', 'PP']]": 0, "['NP', ['JJ', 'NNS', 'CC', 'NNS']]": 0, "['NP', ['``', 'NNP', 'NNP', \"''\"]]": 0, "['S', ['S', ',', 'NP', 'VP', '.']]": 0, "['VP', ['VB', 'PRT']]": 0, "['PRT', ['RP']]": 0, "['VP', ['VBZ', 'ADJP', 'SBAR']]": 0, "['ADJP', ['JJ']]": 0, "['NP', ['NP', ',', 'NP', 'CC', 'NP']]": 0, "['VP', ['VBP', 'NP', 'PP']]": 0, "['NP', ['NP', 'JJ', 'NNS']]": 0, "['NP', ['NNS', 'POS']]": 0, "['NP', ['NP', 'VP']]": 0, "['NP', ['PDT', 'DT', 'NNS']]": 0, "['VP', ['VBN', 'ADVP', ',', 'ADVP', 'S']]": 0, "['ADJP', ['JJ', 'CC', 'JJ']]": 0, "['SBAR', ['WHNP', 'S']]": 0, "['VP', ['VBP', 'PP']]": 0, "Comparison_Arg1_Explicit": 1, "Comparison_Arg1_Implicit": 0, "Comparison_Arg2_Explicit": 0, "Comparison_Arg2_Implicit": 0, "Contingency_Arg1_Explicit": 0, "Contingency_Arg1_Implicit": 2, "Contingency_Arg2_Explicit": 0, "Contingency_Arg2_Implicit": 1, "Expansion_Arg1_Explicit": 0, "Expansion_Arg1_Implicit": 0, "Expansion_Arg2_Explicit": 0, "Expansion_Arg2_Implicit": 1, "Temporal_Arg1_Explicit": 0, "Temporal_Arg1_Implicit": 0, "Temporal_Arg2_Explicit": 0, "Temporal_Arg2_Implicit": 0, "presence_positive_associations": 1, "presence_negative_associations": 1, "ratio_positive_associations": 0.7857142857142857, "ratio_negative_associations": 0.16071428571428573, "between_forward_indicators": 0, "between_backwards_indicators": 0, "between_thesis_indicators": 0, "between_rebuttal_indicators": 0}, "5,6": {"is_a_relation": 0, "num_tokens": 32, "same_sentence": 0, "target_before_source": 0, "intro_or_conc": 0, "num_between": 0, "num_in_paragraph": 4, "share_noun": 0, "num_shared_nouns": 0, "first_or_last": 1, "component_forward_indicators": 1, "context_forward_indicators": 0, "component_backwards_indicators": 0, "context_backwards_indicators": 0, "component_thesis_indicators": 0, "context_thesis_indicators": 0, "component_rebuttal_indicators": 0, "context_rebuttal_indicators": 0, "CC": 2, "CD": 0, "DT": 3, "EX": 0, "FW": 0, "IN": 2, "JJ": 2, "JJR": 0, "JJS": 0, "LS": 0, "MD": 0, "NN": 6, "NNS": 1, "NNP": 0, "NNPS": 0, "PDT": 0, "POS": 0, "PRP": 2, "PRP$": 0, "RB": 3, "RBR": 0, "RBS": 1, "RP": 0, "SYM": 0, "TO": 1, "UH": 0, "VB": 2, "VBD": 0, "VBG": 2, "VBN": 0, "VBP": 2, "VBZ": 1, "WDT": 0, "WP": 0, "WP$": 0, "WRB": 1, "['PP', ['IN', 'NP']]": 0, "['S', ['NP', 'VP']]": 2, "['ROOT', ['S']]": 1, "['NP', ['NP', 'PP']]": 0, "['ADVP', ['RB']]": 0, "['NP', ['DT', 'NN']]": 2, "['NP', ['NNS']]": 0, "['S', ['VP']]": 0, "['VP', ['TO', 'VP']]": 0, "['SBAR', ['IN', 'S']]": 1, "['NP', ['NN']]": 0, "['NP', ['JJ', 'NNS']]": 0, "['VP', ['VB', 'NP']]": 0, "['NP', ['NN', 'NN']]": 0, "['VP', ['VBZ', 'SBAR']]": 0, "['NP', ['PRP']]": 1, "['S', ['NP', 'VP', '.']]": 0, "['NP', ['NP', 'CC', 'NP']]": 0, "['VP', ['VBZ', 'NP']]": 0, "['NP', ['PRP$', 'NN']]": 0, "['NP', ['NML', 'NN']]": 0, "['ADJP', ['RB', 'JJ']]": 0, "['VP', ['VBP', 'PP', 'SBAR']]": 0, "['NP', ['NN', 'NNS']]": 0, "['VP', ['VP', 'CC', 'VP']]": 0, "['VP', ['VB', 'NP', 'PP']]": 0, "['NP', ['NN', 'CC', 'NN']]": 0, "['VP', ['VBP', 'VP']]": 0, "['VP', ['VBP', 'NP']]": 0, "['NP', ['NP', 'SBAR']]": 0, "['WHNP', ['WDT']]": 0, "['NP', ['ADJP', 'NN']]": 0, "['S', ['S', ',', 'CC', 'S', '.']]": 0, "['NP', ['DT', 'JJ', 'CD']]": 0, "['S', ['PP', 'NP', 'VP']]": 0, "['NP', ['DT', 'NML', 'NN']]": 0, "['NML', ['ADVP']]": 0, "['ADVP', ['RBR']]": 0, "['S', ['NP', 'PP']]": 0, "['NP', ['NP', 'ADJP']]": 0, "['NML', ['JJ', 'NNS']]": 0, "['NP', ['CD', 'NN']]": 0, "['NP', ['NN', 'CC', 'NNS']]": 0, "['NP', ['NP', 'NNS']]": 0, "['NP', ['JJ', 'NNS', 'POS']]": 0, "['SBAR', ['IN', 'NN', 'S']]": 0, "['NP', ['PRP$', 'NN', 'CC', 'NN']]": 0, "['NML', ['NN', 'NN', 'CC', 'NN']]": 0, "['VP', ['VBP', 'ADVP', 'VP']]": 0, "['ADVP', ['RBR', 'CC', 'RBR']]": 0, "['VP', ['VBG', 'NP']]": 0, "['NP', ['NNS', 'NNS']]": 0, "['S', ['S', 'CC', 'S', 'CC', 'S', '.']]": 0, "['S', ['NP', ',', 'NP', 'VP']]": 0, "['VP', ['MD', 'VP']]": 0, "['VP', ['VB', 'ADVP']]": 0, "['NP', ['RB']]": 0, "['S', ['ADVP', 'NP', 'VP']]": 0, "['VP', ['VBP', 'RB', 'VP']]": 0, "['VP', ['VB', 'NP', 'S']]": 0, "['NP', ['DT', 'JJR']]": 0, "['VP', ['VBZ', 'S']]": 0, "['SBAR', ['WHADVP', 'S']]": 0, "['WHADVP', ['WRB']]": 0, "['NP', ['DT', 'ADJP', 'NN']]": 0, "['ADJP', ['RBS', 'JJ']]": 0, "['S', ['ADVP', ',', 'NP', 'ADVP', 'VP', '.']]": 0, "['NP', ['JJ', 'NN']]": 0, "['VP', ['VB', 'NP', 'ADVP', 'S', 'SBAR']]": 0, "['VP', ['VBG', 'CC', 'VBG']]": 0, "['S', ['S', ':', 'S', '.']]": 0, "['S', ['NP', 'ADVP', 'VP']]": 0, "['NP', ['DT']]": 0, "['VP', ['VBP', 'NP', 'NP']]": 0, "['NP', ['NNS', 'CC', 'NNS']]": 0, "['S', ['ADVP', ',', 'NP', 'VP', '.']]": 0, "['NP', ['EX']]": 0, "['NP', ['NP', ',', 'NP']]": 0, "['SBAR', ['WHPP', 'S']]": 0, "['WHPP', ['IN', 'WHNP']]": 0, "['VP', ['VBN', 'PP', ',', 'PP']]": 0, "['NP', ['JJ', 'NNS', 'CC', 'NNS']]": 0, "['NP', ['``', 'NNP', 'NNP', \"''\"]]": 0, "['S', ['S', ',', 'NP', 'VP', '.']]": 0, "['VP', ['VB', 'PRT']]": 0, "['PRT', ['RP']]": 0, "['VP', ['VBZ', 'ADJP', 'SBAR']]": 0, "['ADJP', ['JJ']]": 0, "['NP', ['NP', ',', 'NP', 'CC', 'NP']]": 0, "['VP', ['VBP', 'NP', 'PP']]": 0, "['NP', ['NP', 'JJ', 'NNS']]": 0, "['NP', ['NNS', 'POS']]": 0, "['NP', ['NP', 'VP']]": 0, "['NP', ['PDT', 'DT', 'NNS']]": 0, "['VP', ['VBN', 'ADVP', ',', 'ADVP', 'S']]": 0, "['ADJP', ['JJ', 'CC', 'JJ']]": 0, "['SBAR', ['WHNP', 'S']]": 0, "['VP', ['VBP', 'PP']]": 0, "Comparison_Arg1_Explicit": 0, "Comparison_Arg1_Implicit": 0, "Comparison_Arg2_Explicit": 0, "Comparison_Arg2_Implicit": 0, "Contingency_Arg1_Explicit": 0, "Contingency_Arg1_Implicit": 0, "Contingency_Arg2_Explicit": 0, "Contingency_Arg2_Implicit": 1, "Expansion_Arg1_Explicit": 0, "Expansion_Arg1_Implicit": 2, "Expansion_Arg2_Explicit": 0, "Expansion_Arg2_Implicit": 1, "Temporal_Arg1_Explicit": 0, "Temporal_Arg1_Implicit": 0, "Temporal_Arg2_Explicit": 0, "Temporal_Arg2_Implicit": 0, "presence_positive_associations": 1, "presence_negative_associations": 1, "ratio_positive_associations": 0.46875, "ratio_negative_associations": 0.15625, "between_forward_indicators": 0, "between_backwards_indicators": 0, "between_thesis_indicators": 0, "between_rebuttal_indicators": 0}, "5,7": {"is_a_relation": 0, "num_tokens": 36, "same_sentence": 0, "target_before_source": 0, "intro_or_conc": 0, "num_between": 1, "num_in_paragraph": 4, "share_noun": 0, "num_shared_nouns": 0, "first_or_last": 1, "component_forward_indicators": 1, "context_forward_indicators": 0, "component_backwards_indicators": 0, "context_backwards_indicators": 0, "component_thesis_indicators": 0, "context_thesis_indicators": 0, "component_rebuttal_indicators": 0, "context_rebuttal_indicators": 0, "CC": 2, "CD": 0, "DT": 4, "EX": 0, "FW": 0, "IN": 5, "JJ": 1, "JJR": 0, "JJS": 0, "LS": 0, "MD": 0, "NN": 8, "NNS": 6, "NNP": 0, "NNPS": 0, "PDT": 0, "POS": 0, "PRP": 1, "PRP$": 0, "RB": 1, "RBR": 0, "RBS": 1, "RP": 0, "SYM": 0, "TO": 0, "UH": 0, "VB": 0, "VBD": 0, "VBG": 0, "VBN": 0, "VBP": 3, "VBZ": 2, "WDT": 0, "WP": 0, "WP$": 0, "WRB": 1, "['PP', ['IN', 'NP']]": 1, "['S', ['NP', 'VP']]": 2, "['ROOT', ['S']]": 1, "['NP', ['NP', 'PP']]": 0, "['ADVP', ['RB']]": 0, "['NP', ['DT', 'NN']]": 2, "['NP', ['NNS']]": 0, "['S', ['VP']]": 0, "['VP', ['TO', 'VP']]": 0, "['SBAR', ['IN', 'S']]": 1, "['NP', ['NN']]": 0, "['NP', ['JJ', 'NNS']]": 0, "['VP', ['VB', 'NP']]": 0, "['NP', ['NN', 'NN']]": 0, "['VP', ['VBZ', 'SBAR']]": 1, "['NP', ['PRP']]": 0, "['S', ['NP', 'VP', '.']]": 0, "['NP', ['NP', 'CC', 'NP']]": 0, "['VP', ['VBZ', 'NP']]": 0, "['NP', ['PRP$', 'NN']]": 0, "['NP', ['NML', 'NN']]": 0, "['ADJP', ['RB', 'JJ']]": 0, "['VP', ['VBP', 'PP', 'SBAR']]": 0, "['NP', ['NN', 'NNS']]": 0, "['VP', ['VP', 'CC', 'VP']]": 0, "['VP', ['VB', 'NP', 'PP']]": 0, "['NP', ['NN', 'CC', 'NN']]": 0, "['VP', ['VBP', 'VP']]": 0, "['VP', ['VBP', 'NP']]": 0, "['NP', ['NP', 'SBAR']]": 0, "['WHNP', ['WDT']]": 0, "['NP', ['ADJP', 'NN']]": 0, "['S', ['S', ',', 'CC', 'S', '.']]": 0, "['NP', ['DT', 'JJ', 'CD']]": 0, "['S', ['PP', 'NP', 'VP']]": 0, "['NP', ['DT', 'NML', 'NN']]": 0, "['NML', ['ADVP']]": 0, "['ADVP', ['RBR']]": 0, "['S', ['NP', 'PP']]": 0, "['NP', ['NP', 'ADJP']]": 0, "['NML', ['JJ', 'NNS']]": 0, "['NP', ['CD', 'NN']]": 0, "['NP', ['NN', 'CC', 'NNS']]": 0, "['NP', ['NP', 'NNS']]": 0, "['NP', ['JJ', 'NNS', 'POS']]": 0, "['SBAR', ['IN', 'NN', 'S']]": 0, "['NP', ['PRP$', 'NN', 'CC', 'NN']]": 0, "['NML', ['NN', 'NN', 'CC', 'NN']]": 0, "['VP', ['VBP', 'ADVP', 'VP']]": 0, "['ADVP', ['RBR', 'CC', 'RBR']]": 0, "['VP', ['VBG', 'NP']]": 0, "['NP', ['NNS', 'NNS']]": 0, "['S', ['S', 'CC', 'S', 'CC', 'S', '.']]": 0, "['S', ['NP', ',', 'NP', 'VP']]": 0, "['VP', ['MD', 'VP']]": 0, "['VP', ['VB', 'ADVP']]": 0, "['NP', ['RB']]": 0, "['S', ['ADVP', 'NP', 'VP']]": 0, "['VP', ['VBP', 'RB', 'VP']]": 0, "['VP', ['VB', 'NP', 'S']]": 0, "['NP', ['DT', 'JJR']]": 0, "['VP', ['VBZ', 'S']]": 0, "['SBAR', ['WHADVP', 'S']]": 0, "['WHADVP', ['WRB']]": 0, "['NP', ['DT', 'ADJP', 'NN']]": 0, "['ADJP', ['RBS', 'JJ']]": 0, "['S', ['ADVP', ',', 'NP', 'ADVP', 'VP', '.']]": 0, "['NP', ['JJ', 'NN']]": 0, "['VP', ['VB', 'NP', 'ADVP', 'S', 'SBAR']]": 0, "['VP', ['VBG', 'CC', 'VBG']]": 0, "['S', ['S', ':', 'S', '.']]": 0, "['S', ['NP', 'ADVP', 'VP']]": 0, "['NP', ['DT']]": 0, "['VP', ['VBP', 'NP', 'NP']]": 0, "['NP', ['NNS', 'CC', 'NNS']]": 0, "['S', ['ADVP', ',', 'NP', 'VP', '.']]": 0, "['NP', ['EX']]": 0, "['NP', ['NP', ',', 'NP']]": 0, "['SBAR', ['WHPP', 'S']]": 0, "['WHPP', ['IN', 'WHNP']]": 0, "['VP', ['VBN', 'PP', ',', 'PP']]": 0, "['NP', ['JJ', 'NNS', 'CC', 'NNS']]": 0, "['NP', ['``', 'NNP', 'NNP', \"''\"]]": 0, "['S', ['S', ',', 'NP', 'VP', '.']]": 0, "['VP', ['VB', 'PRT']]": 0, "['PRT', ['RP']]": 0, "['VP', ['VBZ', 'ADJP', 'SBAR']]": 0, "['ADJP', ['JJ']]": 0, "['NP', ['NP', ',', 'NP', 'CC', 'NP']]": 0, "['VP', ['VBP', 'NP', 'PP']]": 0, "['NP', ['NP', 'JJ', 'NNS']]": 0, "['NP', ['NNS', 'POS']]": 0, "['NP', ['NP', 'VP']]": 0, "['NP', ['PDT', 'DT', 'NNS']]": 0, "['VP', ['VBN', 'ADVP', ',', 'ADVP', 'S']]": 0, "['ADJP', ['JJ', 'CC', 'JJ']]": 0, "['SBAR', ['WHNP', 'S']]": 0, "['VP', ['VBP', 'PP']]": 0, "Comparison_Arg1_Explicit": 0, "Comparison_Arg1_Implicit": 0, "Comparison_Arg2_Explicit": 0, "Comparison_Arg2_Implicit": 0, "Contingency_Arg1_Explicit": 0, "Contingency_Arg1_Implicit": 0, "Contingency_Arg2_Explicit": 0, "Contingency_Arg2_Implicit": 1, "Expansion_Arg1_Explicit": 1, "Expansion_Arg1_Implicit": 1, "Expansion_Arg2_Explicit": 0, "Expansion_Arg2_Implicit": 1, "Temporal_Arg1_Explicit": 0, "Temporal_Arg1_Implicit": 0, "Temporal_Arg2_Explicit": 0, "Temporal_Arg2_Implicit": 0, "presence_positive_associations": 1, "presence_negative_associations": 1, "ratio_positive_associations": 0.4166666666666667, "ratio_negative_associations": 0.1388888888888889, "between_forward_indicators": 0, "between_backwards_indicators": 0, "between_thesis_indicators": 0, "between_rebuttal_indicators": 0}, "5,8": {"is_a_relation": 0, "num_tokens": 39, "same_sentence": 0, "target_before_source": 0, "intro_or_conc": 0, "num_between": 2, "num_in_paragraph": 4, "share_noun": 0, "num_shared_nouns": 0, "first_or_last": 1, "component_forward_indicators": 1, "context_forward_indicators": 0, "component_backwards_indicators": 1, "context_backwards_indicators": 0, "component_thesis_indicators": 0, "context_thesis_indicators": 0, "component_rebuttal_indicators": 0, "context_rebuttal_indicators": 0, "CC": 2, "CD": 0, "DT": 2, "EX": 1, "FW": 0, "IN": 5, "JJ": 2, "JJR": 0, "JJS": 0, "LS": 0, "MD": 0, "NN": 8, "NNS": 4, "NNP": 2, "NNPS": 0, "PDT": 0, "POS": 0, "PRP": 1, "PRP$": 0, "RB": 0, "RBR": 0, "RBS": 1, "RP": 0, "SYM": 0, "TO": 0, "UH": 0, "VB": 0, "VBD": 0, "VBG": 0, "VBN": 1, "VBP": 3, "VBZ": 1, "WDT": 1, "WP": 0, "WP$": 0, "WRB": 1, "['PP', ['IN', 'NP']]": 1, "['S', ['NP', 'VP']]": 2, "['ROOT', ['S']]": 1, "['NP', ['NP', 'PP']]": 0, "['ADVP', ['RB']]": 0, "['NP', ['DT', 'NN']]": 0, "['NP', ['NNS']]": 0, "['S', ['VP']]": 0, "['VP', ['TO', 'VP']]": 0, "['SBAR', ['IN', 'S']]": 0, "['NP', ['NN']]": 0, "['NP', ['JJ', 'NNS']]": 0, "['VP', ['VB', 'NP']]": 0, "['NP', ['NN', 'NN']]": 0, "['VP', ['VBZ', 'SBAR']]": 0, "['NP', ['PRP']]": 0, "['S', ['NP', 'VP', '.']]": 0, "['NP', ['NP', 'CC', 'NP']]": 0, "['VP', ['VBZ', 'NP']]": 0, "['NP', ['PRP$', 'NN']]": 0, "['NP', ['NML', 'NN']]": 0, "['ADJP', ['RB', 'JJ']]": 0, "['VP', ['VBP', 'PP', 'SBAR']]": 0, "['NP', ['NN', 'NNS']]": 0, "['VP', ['VP', 'CC', 'VP']]": 0, "['VP', ['VB', 'NP', 'PP']]": 0, "['NP', ['NN', 'CC', 'NN']]": 0, "['VP', ['VBP', 'VP']]": 0, "['VP', ['VBP', 'NP']]": 0, "['NP', ['NP', 'SBAR']]": 0, "['WHNP', ['WDT']]": 0, "['NP', ['ADJP', 'NN']]": 0, "['S', ['S', ',', 'CC', 'S', '.']]": 0, "['NP', ['DT', 'JJ', 'CD']]": 0, "['S', ['PP', 'NP', 'VP']]": 0, "['NP', ['DT', 'NML', 'NN']]": 0, "['NML', ['ADVP']]": 0, "['ADVP', ['RBR']]": 0, "['S', ['NP', 'PP']]": 0, "['NP', ['NP', 'ADJP']]": 0, "['NML', ['JJ', 'NNS']]": 0, "['NP', ['CD', 'NN']]": 0, "['NP', ['NN', 'CC', 'NNS']]": 0, "['NP', ['NP', 'NNS']]": 0, "['NP', ['JJ', 'NNS', 'POS']]": 0, "['SBAR', ['IN', 'NN', 'S']]": 0, "['NP', ['PRP$', 'NN', 'CC', 'NN']]": 0, "['NML', ['NN', 'NN', 'CC', 'NN']]": 0, "['VP', ['VBP', 'ADVP', 'VP']]": 0, "['ADVP', ['RBR', 'CC', 'RBR']]": 0, "['VP', ['VBG', 'NP']]": 0, "['NP', ['NNS', 'NNS']]": 0, "['S', ['S', 'CC', 'S', 'CC', 'S', '.']]": 0, "['S', ['NP', ',', 'NP', 'VP']]": 0, "['VP', ['MD', 'VP']]": 0, "['VP', ['VB', 'ADVP']]": 0, "['NP', ['RB']]": 0, "['S', ['ADVP', 'NP', 'VP']]": 0, "['VP', ['VBP', 'RB', 'VP']]": 0, "['VP', ['VB', 'NP', 'S']]": 0, "['NP', ['DT', 'JJR']]": 0, "['VP', ['VBZ', 'S']]": 0, "['SBAR', ['WHADVP', 'S']]": 0, "['WHADVP', ['WRB']]": 0, "['NP', ['DT', 'ADJP', 'NN']]": 0, "['ADJP', ['RBS', 'JJ']]": 0, "['S', ['ADVP', ',', 'NP', 'ADVP', 'VP', '.']]": 0, "['NP', ['JJ', 'NN']]": 0, "['VP', ['VB', 'NP', 'ADVP', 'S', 'SBAR']]": 0, "['VP', ['VBG', 'CC', 'VBG']]": 0, "['S', ['S', ':', 'S', '.']]": 0, "['S', ['NP', 'ADVP', 'VP']]": 0, "['NP', ['DT']]": 0, "['VP', ['VBP', 'NP', 'NP']]": 0, "['NP', ['NNS', 'CC', 'NNS']]": 0, "['S', ['ADVP', ',', 'NP', 'VP', '.']]": 0, "['NP', ['EX']]": 0, "['NP', ['NP', ',', 'NP']]": 0, "['SBAR', ['WHPP', 'S']]": 0, "['WHPP', ['IN', 'WHNP']]": 0, "['VP', ['VBN', 'PP', ',', 'PP']]": 0, "['NP', ['JJ', 'NNS', 'CC', 'NNS']]": 0, "['NP', ['``', 'NNP', 'NNP', \"''\"]]": 0, "['S', ['S', ',', 'NP', 'VP', '.']]": 0, "['VP', ['VB', 'PRT']]": 0, "['PRT', ['RP']]": 0, "['VP', ['VBZ', 'ADJP', 'SBAR']]": 0, "['ADJP', ['JJ']]": 0, "['NP', ['NP', ',', 'NP', 'CC', 'NP']]": 0, "['VP', ['VBP', 'NP', 'PP']]": 0, "['NP', ['NP', 'JJ', 'NNS']]": 0, "['NP', ['NNS', 'POS']]": 0, "['NP', ['NP', 'VP']]": 0, "['NP', ['PDT', 'DT', 'NNS']]": 0, "['VP', ['VBN', 'ADVP', ',', 'ADVP', 'S']]": 0, "['ADJP', ['JJ', 'CC', 'JJ']]": 0, "['SBAR', ['WHNP', 'S']]": 0, "['VP', ['VBP', 'PP']]": 0, "Comparison_Arg1_Explicit": 0, "Comparison_Arg1_Implicit": 0, "Comparison_Arg2_Explicit": 0, "Comparison_Arg2_Implicit": 0, "Contingency_Arg1_Explicit": 0, "Contingency_Arg1_Implicit": 0, "Contingency_Arg2_Explicit": 0, "Contingency_Arg2_Implicit": 1, "Expansion_Arg1_Explicit": 0, "Expansion_Arg1_Implicit": 2, "Expansion_Arg2_Explicit": 0, "Expansion_Arg2_Implicit": 0, "Temporal_Arg1_Explicit": 0, "Temporal_Arg1_Implicit": 0, "Temporal_Arg2_Explicit": 0, "Temporal_Arg2_Implicit": 0, "presence_positive_associations": 1, "presence_negative_associations": 1, "ratio_positive_associations": 0.38461538461538464, "ratio_negative_associations": 0.1282051282051282, "between_forward_indicators": 0, "between_backwards_indicators": 0, "between_thesis_indicators": 0, "between_rebuttal_indicators": 0}, "6,5": {"is_a_relation": 1, "num_tokens": 32, "same_sentence": 0, "target_before_source": 1, "intro_or_conc": 0, "num_between": 0, "num_in_paragraph": 4, "share_noun": 0, "num_shared_nouns": 0, "first_or_last": 1, "component_forward_indicators": 1, "context_forward_indicators": 0, "component_backwards_indicators": 0, "context_backwards_indicators": 0, "component_thesis_indicators": 0, "context_thesis_indicators": 0, "component_rebuttal_indicators": 0, "context_rebuttal_indicators": 0, "CC": 2, "CD": 0, "DT": 3, "EX": 0, "FW": 0, "IN": 2, "JJ": 2, "JJR": 0, "JJS": 0, "LS": 0, "MD": 0, "NN": 6, "NNS": 1, "NNP": 0, "NNPS": 0, "PDT": 0, "POS": 0, "PRP": 2, "PRP$": 0, "RB": 3, "RBR": 0, "RBS": 1, "RP": 0, "SYM": 0, "TO": 1, "UH": 0, "VB": 2, "VBD": 0, "VBG": 2, "VBN": 0, "VBP": 2, "VBZ": 1, "WDT": 0, "WP": 0, "WP$": 0, "WRB": 1, "['PP', ['IN', 'NP']]": 0, "['S', ['NP', 'VP']]": 1, "['ROOT', ['S']]": 1, "['NP', ['NP', 'PP']]": 0, "['ADVP', ['RB']]": 0, "['NP', ['DT', 'NN']]": 1, "['NP', ['NNS']]": 0, "['S', ['VP']]": 0, "['VP', ['TO', 'VP']]": 0, "['SBAR', ['IN', 'S']]": 1, "['NP', ['NN']]": 0, "['NP', ['JJ', 'NNS']]": 0, "['VP', ['VB', 'NP']]": 0, "['NP', ['NN', 'NN']]": 0, "['VP', ['VBZ', 'SBAR']]": 0, "['NP', ['PRP']]": 1, "['S', ['NP', 'VP', '.']]": 0, "['NP', ['NP', 'CC', 'NP']]": 0, "['VP', ['VBZ', 'NP']]": 0, "['NP', ['PRP$', 'NN']]": 0, "['NP', ['NML', 'NN']]": 0, "['ADJP', ['RB', 'JJ']]": 0, "['VP', ['VBP', 'PP', 'SBAR']]": 0, "['NP', ['NN', 'NNS']]": 0, "['VP', ['VP', 'CC', 'VP']]": 0, "['VP', ['VB', 'NP', 'PP']]": 0, "['NP', ['NN', 'CC', 'NN']]": 0, "['VP', ['VBP', 'VP']]": 0, "['VP', ['VBP', 'NP']]": 0, "['NP', ['NP', 'SBAR']]": 0, "['WHNP', ['WDT']]": 0, "['NP', ['ADJP', 'NN']]": 0, "['S', ['S', ',', 'CC', 'S', '.']]": 0, "['NP', ['DT', 'JJ', 'CD']]": 0, "['S', ['PP', 'NP', 'VP']]": 0, "['NP', ['DT', 'NML', 'NN']]": 0, "['NML', ['ADVP']]": 0, "['ADVP', ['RBR']]": 0, "['S', ['NP', 'PP']]": 0, "['NP', ['NP', 'ADJP']]": 0, "['NML', ['JJ', 'NNS']]": 0, "['NP', ['CD', 'NN']]": 0, "['NP', ['NN', 'CC', 'NNS']]": 0, "['NP', ['NP', 'NNS']]": 0, "['NP', ['JJ', 'NNS', 'POS']]": 0, "['SBAR', ['IN', 'NN', 'S']]": 0, "['NP', ['PRP$', 'NN', 'CC', 'NN']]": 0, "['NML', ['NN', 'NN', 'CC', 'NN']]": 0, "['VP', ['VBP', 'ADVP', 'VP']]": 0, "['ADVP', ['RBR', 'CC', 'RBR']]": 0, "['VP', ['VBG', 'NP']]": 0, "['NP', ['NNS', 'NNS']]": 0, "['S', ['S', 'CC', 'S', 'CC', 'S', '.']]": 0, "['S', ['NP', ',', 'NP', 'VP']]": 0, "['VP', ['MD', 'VP']]": 0, "['VP', ['VB', 'ADVP']]": 0, "['NP', ['RB']]": 0, "['S', ['ADVP', 'NP', 'VP']]": 0, "['VP', ['VBP', 'RB', 'VP']]": 0, "['VP', ['VB', 'NP', 'S']]": 0, "['NP', ['DT', 'JJR']]": 0, "['VP', ['VBZ', 'S']]": 0, "['SBAR', ['WHADVP', 'S']]": 0, "['WHADVP', ['WRB']]": 0, "['NP', ['DT', 'ADJP', 'NN']]": 0, "['ADJP', ['RBS', 'JJ']]": 0, "['S', ['ADVP', ',', 'NP', 'ADVP', 'VP', '.']]": 0, "['NP', ['JJ', 'NN']]": 0, "['VP', ['VB', 'NP', 'ADVP', 'S', 'SBAR']]": 0, "['VP', ['VBG', 'CC', 'VBG']]": 0, "['S', ['S', ':', 'S', '.']]": 0, "['S', ['NP', 'ADVP', 'VP']]": 0, "['NP', ['DT']]": 0, "['VP', ['VBP', 'NP', 'NP']]": 0, "['NP', ['NNS', 'CC', 'NNS']]": 0, "['S', ['ADVP', ',', 'NP', 'VP', '.']]": 0, "['NP', ['EX']]": 0, "['NP', ['NP', ',', 'NP']]": 0, "['SBAR', ['WHPP', 'S']]": 0, "['WHPP', ['IN', 'WHNP']]": 0, "['VP', ['VBN', 'PP', ',', 'PP']]": 0, "['NP', ['JJ', 'NNS', 'CC', 'NNS']]": 0, "['NP', ['``', 'NNP', 'NNP', \"''\"]]": 0, "['S', ['S', ',', 'NP', 'VP', '.']]": 0, "['VP', ['VB', 'PRT']]": 0, "['PRT', ['RP']]": 0, "['VP', ['VBZ', 'ADJP', 'SBAR']]": 0, "['ADJP', ['JJ']]": 0, "['NP', ['NP', ',', 'NP', 'CC', 'NP']]": 0, "['VP', ['VBP', 'NP', 'PP']]": 0, "['NP', ['NP', 'JJ', 'NNS']]": 0, "['NP', ['NNS', 'POS']]": 0, "['NP', ['NP', 'VP']]": 0, "['NP', ['PDT', 'DT', 'NNS']]": 0, "['VP', ['VBN', 'ADVP', ',', 'ADVP', 'S']]": 0, "['ADJP', ['JJ', 'CC', 'JJ']]": 0, "['SBAR', ['WHNP', 'S']]": 0, "['VP', ['VBP', 'PP']]": 0, "Comparison_Arg1_Explicit": 0, "Comparison_Arg1_Implicit": 0, "Comparison_Arg2_Explicit": 0, "Comparison_Arg2_Implicit": 0, "Contingency_Arg1_Explicit": 0, "Contingency_Arg1_Implicit": 0, "Contingency_Arg2_Explicit": 0, "Contingency_Arg2_Implicit": 1, "Expansion_Arg1_Explicit": 0, "Expansion_Arg1_Implicit": 2, "Expansion_Arg2_Explicit": 0, "Expansion_Arg2_Implicit": 1, "Temporal_Arg1_Explicit": 0, "Temporal_Arg1_Implicit": 0, "Temporal_Arg2_Explicit": 0, "Temporal_Arg2_Implicit": 0, "presence_positive_associations": 1, "presence_negative_associations": 1, "ratio_positive_associations": 0.59375, "ratio_negative_associations": 0.125, "between_forward_indicators": 0, "between_backwards_indicators": 0, "between_thesis_indicators": 0, "between_rebuttal_indicators": 0}, "6,7": {"is_a_relation": 0, "num_tokens": 40, "same_sentence": 0, "target_before_source": 0, "intro_or_conc": 0, "num_between": 0, "num_in_paragraph": 4, "share_noun": 1, "num_shared_nouns": 1, "first_or_last": 0, "component_forward_indicators": 0, "context_forward_indicators": 0, "component_backwards_indicators": 0, "context_backwards_indicators": 0, "component_thesis_indicators": 0, "context_thesis_indicators": 0, "component_rebuttal_indicators": 0, "context_rebuttal_indicators": 0, "CC": 2, "CD": 0, "DT": 3, "EX": 0, "FW": 0, "IN": 5, "JJ": 1, "JJR": 0, "JJS": 0, "LS": 0, "MD": 0, "NN": 6, "NNS": 7, "NNP": 0, "NNPS": 0, "PDT": 0, "POS": 0, "PRP": 1, "PRP$": 0, "RB": 4, "RBR": 0, "RBS": 0, "RP": 0, "SYM": 0, "TO": 1, "UH": 0, "VB": 2, "VBD": 0, "VBG": 2, "VBN": 0, "VBP": 3, "VBZ": 1, "WDT": 0, "WP": 0, "WP$": 0, "WRB": 0, "['PP', ['IN', 'NP']]": 0, "['S', ['NP', 'VP']]": 1, "['ROOT', ['S']]": 1, "['NP', ['NP', 'PP']]": 0, "['ADVP', ['RB']]": 3, "['NP', ['DT', 'NN']]": 1, "['NP', ['NNS']]": 1, "['S', ['VP']]": 0, "['VP', ['TO', 'VP']]": 0, "['SBAR', ['IN', 'S']]": 1, "['NP', ['NN']]": 0, "['NP', ['JJ', 'NNS']]": 0, "['VP', ['VB', 'NP']]": 0, "['NP', ['NN', 'NN']]": 0, "['VP', ['VBZ', 'SBAR']]": 0, "['NP', ['PRP']]": 0, "['S', ['NP', 'VP', '.']]": 0, "['NP', ['NP', 'CC', 'NP']]": 0, "['VP', ['VBZ', 'NP']]": 0, "['NP', ['PRP$', 'NN']]": 0, "['NP', ['NML', 'NN']]": 0, "['ADJP', ['RB', 'JJ']]": 0, "['VP', ['VBP', 'PP', 'SBAR']]": 0, "['NP', ['NN', 'NNS']]": 0, "['VP', ['VP', 'CC', 'VP']]": 0, "['VP', ['VB', 'NP', 'PP']]": 0, "['NP', ['NN', 'CC', 'NN']]": 0, "['VP', ['VBP', 'VP']]": 0, "['VP', ['VBP', 'NP']]": 0, "['NP', ['NP', 'SBAR']]": 0, "['WHNP', ['WDT']]": 0, "['NP', ['ADJP', 'NN']]": 0, "['S', ['S', ',', 'CC', 'S', '.']]": 0, "['NP', ['DT', 'JJ', 'CD']]": 0, "['S', ['PP', 'NP', 'VP']]": 0, "['NP', ['DT', 'NML', 'NN']]": 0, "['NML', ['ADVP']]": 0, "['ADVP', ['RBR']]": 0, "['S', ['NP', 'PP']]": 0, "['NP', ['NP', 'ADJP']]": 0, "['NML', ['JJ', 'NNS']]": 0, "['NP', ['CD', 'NN']]": 0, "['NP', ['NN', 'CC', 'NNS']]": 0, "['NP', ['NP', 'NNS']]": 0, "['NP', ['JJ', 'NNS', 'POS']]": 0, "['SBAR', ['IN', 'NN', 'S']]": 0, "['NP', ['PRP$', 'NN', 'CC', 'NN']]": 0, "['NML', ['NN', 'NN', 'CC', 'NN']]": 0, "['VP', ['VBP', 'ADVP', 'VP']]": 0, "['ADVP', ['RBR', 'CC', 'RBR']]": 0, "['VP', ['VBG', 'NP']]": 0, "['NP', ['NNS', 'NNS']]": 0, "['S', ['S', 'CC', 'S', 'CC', 'S', '.']]": 0, "['S', ['NP', ',', 'NP', 'VP']]": 0, "['VP', ['MD', 'VP']]": 0, "['VP', ['VB', 'ADVP']]": 0, "['NP', ['RB']]": 0, "['S', ['ADVP', 'NP', 'VP']]": 0, "['VP', ['VBP', 'RB', 'VP']]": 0, "['VP', ['VB', 'NP', 'S']]": 0, "['NP', ['DT', 'JJR']]": 0, "['VP', ['VBZ', 'S']]": 0, "['SBAR', ['WHADVP', 'S']]": 0, "['WHADVP', ['WRB']]": 0, "['NP', ['DT', 'ADJP', 'NN']]": 0, "['ADJP', ['RBS', 'JJ']]": 0, "['S', ['ADVP', ',', 'NP', 'ADVP', 'VP', '.']]": 0, "['NP', ['JJ', 'NN']]": 0, "['VP', ['VB', 'NP', 'ADVP', 'S', 'SBAR']]": 0, "['VP', ['VBG', 'CC', 'VBG']]": 0, "['S', ['S', ':', 'S', '.']]": 0, "['S', ['NP', 'ADVP', 'VP']]": 0, "['NP', ['DT']]": 0, "['VP', ['VBP', 'NP', 'NP']]": 0, "['NP', ['NNS', 'CC', 'NNS']]": 0, "['S', ['ADVP', ',', 'NP', 'VP', '.']]": 0, "['NP', ['EX']]": 0, "['NP', ['NP', ',', 'NP']]": 0, "['SBAR', ['WHPP', 'S']]": 0, "['WHPP', ['IN', 'WHNP']]": 0, "['VP', ['VBN', 'PP', ',', 'PP']]": 0, "['NP', ['JJ', 'NNS', 'CC', 'NNS']]": 0, "['NP', ['``', 'NNP', 'NNP', \"''\"]]": 0, "['S', ['S', ',', 'NP', 'VP', '.']]": 0, "['VP', ['VB', 'PRT']]": 0, "['PRT', ['RP']]": 0, "['VP', ['VBZ', 'ADJP', 'SBAR']]": 0, "['ADJP', ['JJ']]": 0, "['NP', ['NP', ',', 'NP', 'CC', 'NP']]": 0, "['VP', ['VBP', 'NP', 'PP']]": 0, "['NP', ['NP', 'JJ', 'NNS']]": 0, "['NP', ['NNS', 'POS']]": 0, "['NP', ['NP', 'VP']]": 0, "['NP', ['PDT', 'DT', 'NNS']]": 0, "['VP', ['VBN', 'ADVP', ',', 'ADVP', 'S']]": 0, "['ADJP', ['JJ', 'CC', 'JJ']]": 0, "['SBAR', ['WHNP', 'S']]": 0, "['VP', ['VBP', 'PP']]": 0, "Comparison_Arg1_Explicit": 0, "Comparison_Arg1_Implicit": 0, "Comparison_Arg2_Explicit": 0, "Comparison_Arg2_Implicit": 0, "Contingency_Arg1_Explicit": 0, "Contingency_Arg1_Implicit": 0, "Contingency_Arg2_Explicit": 0, "Contingency_Arg2_Implicit": 0, "Expansion_Arg1_Explicit": 1, "Expansion_Arg1_Implicit": 1, "Expansion_Arg2_Explicit": 0, "Expansion_Arg2_Implicit": 2, "Temporal_Arg1_Explicit": 0, "Temporal_Arg1_Implicit": 0, "Temporal_Arg2_Explicit": 0, "Temporal_Arg2_Implicit": 0, "presence_positive_associations": 1, "presence_negative_associations": 1, "ratio_positive_associations": 0.475, "ratio_negative_associations": 0.1, "between_forward_indicators": 0, "between_backwards_indicators": 0, "between_thesis_indicators": 0, "between_rebuttal_indicators": 0}, "6,8": {"is_a_relation": 0, "num_tokens": 43, "same_sentence": 0, "target_before_source": 0, "intro_or_conc": 0, "num_between": 1, "num_in_paragraph": 4, "share_noun": 0, "num_shared_nouns": 0, "first_or_last": 1, "component_forward_indicators": 0, "context_forward_indicators": 0, "component_backwards_indicators": 1, "context_backwards_indicators": 0, "component_thesis_indicators": 0, "context_thesis_indicators": 0, "component_rebuttal_indicators": 0, "context_rebuttal_indicators": 0, "CC": 2, "CD": 0, "DT": 1, "EX": 1, "FW": 0, "IN": 5, "JJ": 2, "JJR": 0, "JJS": 0, "LS": 0, "MD": 0, "NN": 6, "NNS": 5, "NNP": 2, "NNPS": 0, "PDT": 0, "POS": 0, "PRP": 1, "PRP$": 0, "RB": 3, "RBR": 0, "RBS": 0, "RP": 0, "SYM": 0, "TO": 1, "UH": 0, "VB": 2, "VBD": 0, "VBG": 2, "VBN": 1, "VBP": 3, "VBZ": 0, "WDT": 1, "WP": 0, "WP$": 0, "WRB": 0, "['PP', ['IN', 'NP']]": 0, "['S', ['NP', 'VP']]": 1, "['ROOT', ['S']]": 1, "['NP', ['NP', 'PP']]": 0, "['ADVP', ['RB']]": 3, "['NP', ['DT', 'NN']]": 0, "['NP', ['NNS']]": 1, "['S', ['VP']]": 0, "['VP', ['TO', 'VP']]": 0, "['SBAR', ['IN', 'S']]": 0, "['NP', ['NN']]": 0, "['NP', ['JJ', 'NNS']]": 0, "['VP', ['VB', 'NP']]": 0, "['NP', ['NN', 'NN']]": 0, "['VP', ['VBZ', 'SBAR']]": 0, "['NP', ['PRP']]": 0, "['S', ['NP', 'VP', '.']]": 0, "['NP', ['NP', 'CC', 'NP']]": 0, "['VP', ['VBZ', 'NP']]": 0, "['NP', ['PRP$', 'NN']]": 0, "['NP', ['NML', 'NN']]": 0, "['ADJP', ['RB', 'JJ']]": 0, "['VP', ['VBP', 'PP', 'SBAR']]": 0, "['NP', ['NN', 'NNS']]": 0, "['VP', ['VP', 'CC', 'VP']]": 0, "['VP', ['VB', 'NP', 'PP']]": 0, "['NP', ['NN', 'CC', 'NN']]": 0, "['VP', ['VBP', 'VP']]": 1, "['VP', ['VBP', 'NP']]": 0, "['NP', ['NP', 'SBAR']]": 0, "['WHNP', ['WDT']]": 0, "['NP', ['ADJP', 'NN']]": 0, "['S', ['S', ',', 'CC', 'S', '.']]": 0, "['NP', ['DT', 'JJ', 'CD']]": 0, "['S', ['PP', 'NP', 'VP']]": 0, "['NP', ['DT', 'NML', 'NN']]": 0, "['NML', ['ADVP']]": 0, "['ADVP', ['RBR']]": 0, "['S', ['NP', 'PP']]": 0, "['NP', ['NP', 'ADJP']]": 0, "['NML', ['JJ', 'NNS']]": 0, "['NP', ['CD', 'NN']]": 0, "['NP', ['NN', 'CC', 'NNS']]": 0, "['NP', ['NP', 'NNS']]": 0, "['NP', ['JJ', 'NNS', 'POS']]": 0, "['SBAR', ['IN', 'NN', 'S']]": 0, "['NP', ['PRP$', 'NN', 'CC', 'NN']]": 0, "['NML', ['NN', 'NN', 'CC', 'NN']]": 0, "['VP', ['VBP', 'ADVP', 'VP']]": 0, "['ADVP', ['RBR', 'CC', 'RBR']]": 0, "['VP', ['VBG', 'NP']]": 0, "['NP', ['NNS', 'NNS']]": 0, "['S', ['S', 'CC', 'S', 'CC', 'S', '.']]": 0, "['S', ['NP', ',', 'NP', 'VP']]": 0, "['VP', ['MD', 'VP']]": 0, "['VP', ['VB', 'ADVP']]": 0, "['NP', ['RB']]": 0, "['S', ['ADVP', 'NP', 'VP']]": 0, "['VP', ['VBP', 'RB', 'VP']]": 0, "['VP', ['VB', 'NP', 'S']]": 0, "['NP', ['DT', 'JJR']]": 0, "['VP', ['VBZ', 'S']]": 0, "['SBAR', ['WHADVP', 'S']]": 0, "['WHADVP', ['WRB']]": 0, "['NP', ['DT', 'ADJP', 'NN']]": 0, "['ADJP', ['RBS', 'JJ']]": 0, "['S', ['ADVP', ',', 'NP', 'ADVP', 'VP', '.']]": 0, "['NP', ['JJ', 'NN']]": 0, "['VP', ['VB', 'NP', 'ADVP', 'S', 'SBAR']]": 0, "['VP', ['VBG', 'CC', 'VBG']]": 0, "['S', ['S', ':', 'S', '.']]": 0, "['S', ['NP', 'ADVP', 'VP']]": 0, "['NP', ['DT']]": 0, "['VP', ['VBP', 'NP', 'NP']]": 0, "['NP', ['NNS', 'CC', 'NNS']]": 0, "['S', ['ADVP', ',', 'NP', 'VP', '.']]": 0, "['NP', ['EX']]": 0, "['NP', ['NP', ',', 'NP']]": 0, "['SBAR', ['WHPP', 'S']]": 0, "['WHPP', ['IN', 'WHNP']]": 0, "['VP', ['VBN', 'PP', ',', 'PP']]": 0, "['NP', ['JJ', 'NNS', 'CC', 'NNS']]": 0, "['NP', ['``', 'NNP', 'NNP', \"''\"]]": 0, "['S', ['S', ',', 'NP', 'VP', '.']]": 0, "['VP', ['VB', 'PRT']]": 0, "['PRT', ['RP']]": 0, "['VP', ['VBZ', 'ADJP', 'SBAR']]": 0, "['ADJP', ['JJ']]": 0, "['NP', ['NP', ',', 'NP', 'CC', 'NP']]": 0, "['VP', ['VBP', 'NP', 'PP']]": 0, "['NP', ['NP', 'JJ', 'NNS']]": 0, "['NP', ['NNS', 'POS']]": 0, "['NP', ['NP', 'VP']]": 0, "['NP', ['PDT', 'DT', 'NNS']]": 0, "['VP', ['VBN', 'ADVP', ',', 'ADVP', 'S']]": 0, "['ADJP', ['JJ', 'CC', 'JJ']]": 0, "['SBAR', ['WHNP', 'S']]": 0, "['VP', ['VBP', 'PP']]": 0, "Comparison_Arg1_Explicit": 0, "Comparison_Arg1_Implicit": 0, "Comparison_Arg2_Explicit": 0, "Comparison_Arg2_Implicit": 0, "Contingency_Arg1_Explicit": 0, "Contingency_Arg1_Implicit": 0, "Contingency_Arg2_Explicit": 0, "Contingency_Arg2_Implicit": 0, "Expansion_Arg1_Explicit": 0, "Expansion_Arg1_Implicit": 2, "Expansion_Arg2_Explicit": 0, "Expansion_Arg2_Implicit": 1, "Temporal_Arg1_Explicit": 0, "Temporal_Arg1_Implicit": 0, "Temporal_Arg2_Explicit": 0, "Temporal_Arg2_Implicit": 0, "presence_positive_associations": 1, "presence_negative_associations": 1, "ratio_positive_associations": 0.4418604651162791, "ratio_negative_associations": 0.09302325581395349, "between_forward_indicators": 0, "between_backwards_indicators": 0, "between_thesis_indicators": 0, "between_rebuttal_indicators": 0}, "7,5": {"is_a_relation": 1, "num_tokens": 36, "same_sentence": 0, "target_before_source": 1, "intro_or_conc": 0, "num_between": 1, "num_in_paragraph": 4, "share_noun": 0, "num_shared_nouns": 0, "first_or_last": 1, "component_forward_indicators": 1, "context_forward_indicators": 0, "component_backwards_indicators": 0, "context_backwards_indicators": 0, "component_thesis_indicators": 0, "context_thesis_indicators": 0, "component_rebuttal_indicators": 0, "context_rebuttal_indicators": 0, "CC": 2, "CD": 0, "DT": 4, "EX": 0, "FW": 0, "IN": 5, "JJ": 1, "JJR": 0, "JJS": 0, "LS": 0, "MD": 0, "NN": 8, "NNS": 6, "NNP": 0, "NNPS": 0, "PDT": 0, "POS": 0, "PRP": 1, "PRP$": 0, "RB": 1, "RBR": 0, "RBS": 1, "RP": 0, "SYM": 0, "TO": 0, "UH": 0, "VB": 0, "VBD": 0, "VBG": 0, "VBN": 0, "VBP": 3, "VBZ": 2, "WDT": 0, "WP": 0, "WP$": 0, "WRB": 1, "['PP', ['IN', 'NP']]": 3, "['S', ['NP', 'VP']]": 2, "['ROOT', ['S']]": 1, "['NP', ['NP', 'PP']]": 0, "['ADVP', ['RB']]": 0, "['NP', ['DT', 'NN']]": 1, "['NP', ['NNS']]": 0, "['S', ['VP']]": 0, "['VP', ['TO', 'VP']]": 0, "['SBAR', ['IN', 'S']]": 1, "['NP', ['NN']]": 0, "['NP', ['JJ', 'NNS']]": 0, "['VP', ['VB', 'NP']]": 0, "['NP', ['NN', 'NN']]": 0, "['VP', ['VBZ', 'SBAR']]": 1, "['NP', ['PRP']]": 0, "['S', ['NP', 'VP', '.']]": 0, "['NP', ['NP', 'CC', 'NP']]": 0, "['VP', ['VBZ', 'NP']]": 0, "['NP', ['PRP$', 'NN']]": 0, "['NP', ['NML', 'NN']]": 0, "['ADJP', ['RB', 'JJ']]": 0, "['VP', ['VBP', 'PP', 'SBAR']]": 0, "['NP', ['NN', 'NNS']]": 0, "['VP', ['VP', 'CC', 'VP']]": 0, "['VP', ['VB', 'NP', 'PP']]": 0, "['NP', ['NN', 'CC', 'NN']]": 0, "['VP', ['VBP', 'VP']]": 0, "['VP', ['VBP', 'NP']]": 0, "['NP', ['NP', 'SBAR']]": 0, "['WHNP', ['WDT']]": 0, "['NP', ['ADJP', 'NN']]": 0, "['S', ['S', ',', 'CC', 'S', '.']]": 0, "['NP', ['DT', 'JJ', 'CD']]": 0, "['S', ['PP', 'NP', 'VP']]": 0, "['NP', ['DT', 'NML', 'NN']]": 0, "['NML', ['ADVP']]": 0, "['ADVP', ['RBR']]": 0, "['S', ['NP', 'PP']]": 0, "['NP', ['NP', 'ADJP']]": 0, "['NML', ['JJ', 'NNS']]": 0, "['NP', ['CD', 'NN']]": 0, "['NP', ['NN', 'CC', 'NNS']]": 0, "['NP', ['NP', 'NNS']]": 0, "['NP', ['JJ', 'NNS', 'POS']]": 0, "['SBAR', ['IN', 'NN', 'S']]": 0, "['NP', ['PRP$', 'NN', 'CC', 'NN']]": 0, "['NML', ['NN', 'NN', 'CC', 'NN']]": 0, "['VP', ['VBP', 'ADVP', 'VP']]": 0, "['ADVP', ['RBR', 'CC', 'RBR']]": 0, "['VP', ['VBG', 'NP']]": 0, "['NP', ['NNS', 'NNS']]": 0, "['S', ['S', 'CC', 'S', 'CC', 'S', '.']]": 0, "['S', ['NP', ',', 'NP', 'VP']]": 0, "['VP', ['MD', 'VP']]": 0, "['VP', ['VB', 'ADVP']]": 0, "['NP', ['RB']]": 0, "['S', ['ADVP', 'NP', 'VP']]": 0, "['VP', ['VBP', 'RB', 'VP']]": 0, "['VP', ['VB', 'NP', 'S']]": 0, "['NP', ['DT', 'JJR']]": 0, "['VP', ['VBZ', 'S']]": 0, "['SBAR', ['WHADVP', 'S']]": 0, "['WHADVP', ['WRB']]": 0, "['NP', ['DT', 'ADJP', 'NN']]": 0, "['ADJP', ['RBS', 'JJ']]": 0, "['S', ['ADVP', ',', 'NP', 'ADVP', 'VP', '.']]": 0, "['NP', ['JJ', 'NN']]": 0, "['VP', ['VB', 'NP', 'ADVP', 'S', 'SBAR']]": 0, "['VP', ['VBG', 'CC', 'VBG']]": 0, "['S', ['S', ':', 'S', '.']]": 0, "['S', ['NP', 'ADVP', 'VP']]": 0, "['NP', ['DT']]": 0, "['VP', ['VBP', 'NP', 'NP']]": 0, "['NP', ['NNS', 'CC', 'NNS']]": 0, "['S', ['ADVP', ',', 'NP', 'VP', '.']]": 0, "['NP', ['EX']]": 0, "['NP', ['NP', ',', 'NP']]": 0, "['SBAR', ['WHPP', 'S']]": 0, "['WHPP', ['IN', 'WHNP']]": 0, "['VP', ['VBN', 'PP', ',', 'PP']]": 0, "['NP', ['JJ', 'NNS', 'CC', 'NNS']]": 0, "['NP', ['``', 'NNP', 'NNP', \"''\"]]": 0, "['S', ['S', ',', 'NP', 'VP', '.']]": 0, "['VP', ['VB', 'PRT']]": 0, "['PRT', ['RP']]": 0, "['VP', ['VBZ', 'ADJP', 'SBAR']]": 0, "['ADJP', ['JJ']]": 0, "['NP', ['NP', ',', 'NP', 'CC', 'NP']]": 0, "['VP', ['VBP', 'NP', 'PP']]": 0, "['NP', ['NP', 'JJ', 'NNS']]": 0, "['NP', ['NNS', 'POS']]": 0, "['NP', ['NP', 'VP']]": 0, "['NP', ['PDT', 'DT', 'NNS']]": 0, "['VP', ['VBN', 'ADVP', ',', 'ADVP', 'S']]": 0, "['ADJP', ['JJ', 'CC', 'JJ']]": 0, "['SBAR', ['WHNP', 'S']]": 0, "['VP', ['VBP', 'PP']]": 0, "Comparison_Arg1_Explicit": 0, "Comparison_Arg1_Implicit": 0, "Comparison_Arg2_Explicit": 0, "Comparison_Arg2_Implicit": 0, "Contingency_Arg1_Explicit": 0, "Contingency_Arg1_Implicit": 0, "Contingency_Arg2_Explicit": 0, "Contingency_Arg2_Implicit": 1, "Expansion_Arg1_Explicit": 1, "Expansion_Arg1_Implicit": 1, "Expansion_Arg2_Explicit": 0, "Expansion_Arg2_Implicit": 1, "Temporal_Arg1_Explicit": 0, "Temporal_Arg1_Implicit": 0, "Temporal_Arg2_Explicit": 0, "Temporal_Arg2_Implicit": 0, "presence_positive_associations": 1, "presence_negative_associations": 1, "ratio_positive_associations": 0.5555555555555556, "ratio_negative_associations": 0.1388888888888889, "between_forward_indicators": 0, "between_backwards_indicators": 0, "between_thesis_indicators": 0, "between_rebuttal_indicators": 0}, "7,6": {"is_a_relation": 0, "num_tokens": 40, "same_sentence": 0, "target_before_source": 1, "intro_or_conc": 0, "num_between": 0, "num_in_paragraph": 4, "share_noun": 1, "num_shared_nouns": 1, "first_or_last": 0, "component_forward_indicators": 0, "context_forward_indicators": 0, "component_backwards_indicators": 0, "context_backwards_indicators": 0, "component_thesis_indicators": 0, "context_thesis_indicators": 0, "component_rebuttal_indicators": 0, "context_rebuttal_indicators": 0, "CC": 2, "CD": 0, "DT": 3, "EX": 0, "FW": 0, "IN": 5, "JJ": 1, "JJR": 0, "JJS": 0, "LS": 0, "MD": 0, "NN": 6, "NNS": 7, "NNP": 0, "NNPS": 0, "PDT": 0, "POS": 0, "PRP": 1, "PRP$": 0, "RB": 4, "RBR": 0, "RBS": 0, "RP": 0, "SYM": 0, "TO": 1, "UH": 0, "VB": 2, "VBD": 0, "VBG": 2, "VBN": 0, "VBP": 3, "VBZ": 1, "WDT": 0, "WP": 0, "WP$": 0, "WRB": 0, "['PP', ['IN', 'NP']]": 0, "['S', ['NP', 'VP']]": 2, "['ROOT', ['S']]": 1, "['NP', ['NP', 'PP']]": 0, "['ADVP', ['RB']]": 1, "['NP', ['DT', 'NN']]": 1, "['NP', ['NNS']]": 4, "['S', ['VP']]": 0, "['VP', ['TO', 'VP']]": 0, "['SBAR', ['IN', 'S']]": 1, "['NP', ['NN']]": 0, "['NP', ['JJ', 'NNS']]": 0, "['VP', ['VB', 'NP']]": 0, "['NP', ['NN', 'NN']]": 0, "['VP', ['VBZ', 'SBAR']]": 0, "['NP', ['PRP']]": 0, "['S', ['NP', 'VP', '.']]": 0, "['NP', ['NP', 'CC', 'NP']]": 0, "['VP', ['VBZ', 'NP']]": 0, "['NP', ['PRP$', 'NN']]": 0, "['NP', ['NML', 'NN']]": 0, "['ADJP', ['RB', 'JJ']]": 0, "['VP', ['VBP', 'PP', 'SBAR']]": 0, "['NP', ['NN', 'NNS']]": 0, "['VP', ['VP', 'CC', 'VP']]": 0, "['VP', ['VB', 'NP', 'PP']]": 0, "['NP', ['NN', 'CC', 'NN']]": 0, "['VP', ['VBP', 'VP']]": 0, "['VP', ['VBP', 'NP']]": 0, "['NP', ['NP', 'SBAR']]": 0, "['WHNP', ['WDT']]": 0, "['NP', ['ADJP', 'NN']]": 0, "['S', ['S', ',', 'CC', 'S', '.']]": 0, "['NP', ['DT', 'JJ', 'CD']]": 0, "['S', ['PP', 'NP', 'VP']]": 0, "['NP', ['DT', 'NML', 'NN']]": 0, "['NML', ['ADVP']]": 0, "['ADVP', ['RBR']]": 0, "['S', ['NP', 'PP']]": 0, "['NP', ['NP', 'ADJP']]": 0, "['NML', ['JJ', 'NNS']]": 0, "['NP', ['CD', 'NN']]": 0, "['NP', ['NN', 'CC', 'NNS']]": 0, "['NP', ['NP', 'NNS']]": 0, "['NP', ['JJ', 'NNS', 'POS']]": 0, "['SBAR', ['IN', 'NN', 'S']]": 0, "['NP', ['PRP$', 'NN', 'CC', 'NN']]": 0, "['NML', ['NN', 'NN', 'CC', 'NN']]": 0, "['VP', ['VBP', 'ADVP', 'VP']]": 0, "['ADVP', ['RBR', 'CC', 'RBR']]": 0, "['VP', ['VBG', 'NP']]": 0, "['NP', ['NNS', 'NNS']]": 0, "['S', ['S', 'CC', 'S', 'CC', 'S', '.']]": 0, "['S', ['NP', ',', 'NP', 'VP']]": 0, "['VP', ['MD', 'VP']]": 0, "['VP', ['VB', 'ADVP']]": 0, "['NP', ['RB']]": 0, "['S', ['ADVP', 'NP', 'VP']]": 0, "['VP', ['VBP', 'RB', 'VP']]": 0, "['VP', ['VB', 'NP', 'S']]": 0, "['NP', ['DT', 'JJR']]": 0, "['VP', ['VBZ', 'S']]": 0, "['SBAR', ['WHADVP', 'S']]": 0, "['WHADVP', ['WRB']]": 0, "['NP', ['DT', 'ADJP', 'NN']]": 0, "['ADJP', ['RBS', 'JJ']]": 0, "['S', ['ADVP', ',', 'NP', 'ADVP', 'VP', '.']]": 0, "['NP', ['JJ', 'NN']]": 0, "['VP', ['VB', 'NP', 'ADVP', 'S', 'SBAR']]": 0, "['VP', ['VBG', 'CC', 'VBG']]": 0, "['S', ['S', ':', 'S', '.']]": 0, "['S', ['NP', 'ADVP', 'VP']]": 0, "['NP', ['DT']]": 0, "['VP', ['VBP', 'NP', 'NP']]": 0, "['NP', ['NNS', 'CC', 'NNS']]": 0, "['S', ['ADVP', ',', 'NP', 'VP', '.']]": 0, "['NP', ['EX']]": 0, "['NP', ['NP', ',', 'NP']]": 0, "['SBAR', ['WHPP', 'S']]": 0, "['WHPP', ['IN', 'WHNP']]": 0, "['VP', ['VBN', 'PP', ',', 'PP']]": 0, "['NP', ['JJ', 'NNS', 'CC', 'NNS']]": 0, "['NP', ['``', 'NNP', 'NNP', \"''\"]]": 0, "['S', ['S', ',', 'NP', 'VP', '.']]": 0, "['VP', ['VB', 'PRT']]": 0, "['PRT', ['RP']]": 0, "['VP', ['VBZ', 'ADJP', 'SBAR']]": 0, "['ADJP', ['JJ']]": 0, "['NP', ['NP', ',', 'NP', 'CC', 'NP']]": 0, "['VP', ['VBP', 'NP', 'PP']]": 0, "['NP', ['NP', 'JJ', 'NNS']]": 0, "['NP', ['NNS', 'POS']]": 0, "['NP', ['NP', 'VP']]": 0, "['NP', ['PDT', 'DT', 'NNS']]": 0, "['VP', ['VBN', 'ADVP', ',', 'ADVP', 'S']]": 0, "['ADJP', ['JJ', 'CC', 'JJ']]": 0, "['SBAR', ['WHNP', 'S']]": 0, "['VP', ['VBP', 'PP']]": 0, "Comparison_Arg1_Explicit": 0, "Comparison_Arg1_Implicit": 0, "Comparison_Arg2_Explicit": 0, "Comparison_Arg2_Implicit": 0, "Contingency_Arg1_Explicit": 0, "Contingency_Arg1_Implicit": 0, "Contingency_Arg2_Explicit": 0, "Contingency_Arg2_Implicit": 0, "Expansion_Arg1_Explicit": 1, "Expansion_Arg1_Implicit": 1, "Expansion_Arg2_Explicit": 0, "Expansion_Arg2_Implicit": 2, "Temporal_Arg1_Explicit": 0, "Temporal_Arg1_Implicit": 0, "Temporal_Arg2_Explicit": 0, "Temporal_Arg2_Implicit": 0, "presence_positive_associations": 1, "presence_negative_associations": 1, "ratio_positive_associations": 0.5, "ratio_negative_associations": 0.125, "between_forward_indicators": 0, "between_backwards_indicators": 0, "between_thesis_indicators": 0, "between_rebuttal_indicators": 0}, "7,8": {"is_a_relation": 0, "num_tokens": 47, "same_sentence": 0, "target_before_source": 0, "intro_or_conc": 0, "num_between": 0, "num_in_paragraph": 4, "share_noun": 1, "num_shared_nouns": 1, "first_or_last": 1, "component_forward_indicators": 0, "context_forward_indicators": 0, "component_backwards_indicators": 1, "context_backwards_indicators": 0, "component_thesis_indicators": 0, "context_thesis_indicators": 0, "component_rebuttal_indicators": 0, "context_rebuttal_indicators": 0, "CC": 2, "CD": 0, "DT": 2, "EX": 1, "FW": 0, "IN": 8, "JJ": 1, "JJR": 0, "JJS": 0, "LS": 0, "MD": 0, "NN": 8, "NNS": 10, "NNP": 2, "NNPS": 0, "PDT": 0, "POS": 0, "PRP": 0, "PRP$": 0, "RB": 1, "RBR": 0, "RBS": 0, "RP": 0, "SYM": 0, "TO": 0, "UH": 0, "VB": 0, "VBD": 0, "VBG": 0, "VBN": 1, "VBP": 4, "VBZ": 1, "WDT": 1, "WP": 0, "WP$": 0, "WRB": 0, "['PP', ['IN', 'NP']]": 3, "['S', ['NP', 'VP']]": 2, "['ROOT', ['S']]": 1, "['NP', ['NP', 'PP']]": 3, "['ADVP', ['RB']]": 1, "['NP', ['DT', 'NN']]": 0, "['NP', ['NNS']]": 4, "['S', ['VP']]": 0, "['VP', ['TO', 'VP']]": 0, "['SBAR', ['IN', 'S']]": 0, "['NP', ['NN']]": 1, "['NP', ['JJ', 'NNS']]": 0, "['VP', ['VB', 'NP']]": 0, "['NP', ['NN', 'NN']]": 1, "['VP', ['VBZ', 'SBAR']]": 0, "['NP', ['PRP']]": 0, "['S', ['NP', 'VP', '.']]": 0, "['NP', ['NP', 'CC', 'NP']]": 0, "['VP', ['VBZ', 'NP']]": 0, "['NP', ['PRP$', 'NN']]": 0, "['NP', ['NML', 'NN']]": 0, "['ADJP', ['RB', 'JJ']]": 0, "['VP', ['VBP', 'PP', 'SBAR']]": 0, "['NP', ['NN', 'NNS']]": 0, "['VP', ['VP', 'CC', 'VP']]": 0, "['VP', ['VB', 'NP', 'PP']]": 0, "['NP', ['NN', 'CC', 'NN']]": 0, "['VP', ['VBP', 'VP']]": 0, "['VP', ['VBP', 'NP']]": 1, "['NP', ['NP', 'SBAR']]": 0, "['WHNP', ['WDT']]": 0, "['NP', ['ADJP', 'NN']]": 0, "['S', ['S', ',', 'CC', 'S', '.']]": 0, "['NP', ['DT', 'JJ', 'CD']]": 0, "['S', ['PP', 'NP', 'VP']]": 0, "['NP', ['DT', 'NML', 'NN']]": 0, "['NML', ['ADVP']]": 0, "['ADVP', ['RBR']]": 0, "['S', ['NP', 'PP']]": 0, "['NP', ['NP', 'ADJP']]": 0, "['NML', ['JJ', 'NNS']]": 0, "['NP', ['CD', 'NN']]": 0, "['NP', ['NN', 'CC', 'NNS']]": 0, "['NP', ['NP', 'NNS']]": 0, "['NP', ['JJ', 'NNS', 'POS']]": 0, "['SBAR', ['IN', 'NN', 'S']]": 0, "['NP', ['PRP$', 'NN', 'CC', 'NN']]": 0, "['NML', ['NN', 'NN', 'CC', 'NN']]": 0, "['VP', ['VBP', 'ADVP', 'VP']]": 0, "['ADVP', ['RBR', 'CC', 'RBR']]": 0, "['VP', ['VBG', 'NP']]": 0, "['NP', ['NNS', 'NNS']]": 0, "['S', ['S', 'CC', 'S', 'CC', 'S', '.']]": 0, "['S', ['NP', ',', 'NP', 'VP']]": 0, "['VP', ['MD', 'VP']]": 0, "['VP', ['VB', 'ADVP']]": 0, "['NP', ['RB']]": 0, "['S', ['ADVP', 'NP', 'VP']]": 0, "['VP', ['VBP', 'RB', 'VP']]": 0, "['VP', ['VB', 'NP', 'S']]": 0, "['NP', ['DT', 'JJR']]": 0, "['VP', ['VBZ', 'S']]": 0, "['SBAR', ['WHADVP', 'S']]": 0, "['WHADVP', ['WRB']]": 0, "['NP', ['DT', 'ADJP', 'NN']]": 0, "['ADJP', ['RBS', 'JJ']]": 0, "['S', ['ADVP', ',', 'NP', 'ADVP', 'VP', '.']]": 0, "['NP', ['JJ', 'NN']]": 0, "['VP', ['VB', 'NP', 'ADVP', 'S', 'SBAR']]": 0, "['VP', ['VBG', 'CC', 'VBG']]": 0, "['S', ['S', ':', 'S', '.']]": 0, "['S', ['NP', 'ADVP', 'VP']]": 0, "['NP', ['DT']]": 0, "['VP', ['VBP', 'NP', 'NP']]": 0, "['NP', ['NNS', 'CC', 'NNS']]": 0, "['S', ['ADVP', ',', 'NP', 'VP', '.']]": 0, "['NP', ['EX']]": 0, "['NP', ['NP', ',', 'NP']]": 0, "['SBAR', ['WHPP', 'S']]": 0, "['WHPP', ['IN', 'WHNP']]": 0, "['VP', ['VBN', 'PP', ',', 'PP']]": 0, "['NP', ['JJ', 'NNS', 'CC', 'NNS']]": 0, "['NP', ['``', 'NNP', 'NNP', \"''\"]]": 0, "['S', ['S', ',', 'NP', 'VP', '.']]": 0, "['VP', ['VB', 'PRT']]": 0, "['PRT', ['RP']]": 0, "['VP', ['VBZ', 'ADJP', 'SBAR']]": 0, "['ADJP', ['JJ']]": 0, "['NP', ['NP', ',', 'NP', 'CC', 'NP']]": 0, "['VP', ['VBP', 'NP', 'PP']]": 0, "['NP', ['NP', 'JJ', 'NNS']]": 0, "['NP', ['NNS', 'POS']]": 0, "['NP', ['NP', 'VP']]": 0, "['NP', ['PDT', 'DT', 'NNS']]": 0, "['VP', ['VBN', 'ADVP', ',', 'ADVP', 'S']]": 0, "['ADJP', ['JJ', 'CC', 'JJ']]": 0, "['SBAR', ['WHNP', 'S']]": 0, "['VP', ['VBP', 'PP']]": 0, "Comparison_Arg1_Explicit": 0, "Comparison_Arg1_Implicit": 0, "Comparison_Arg2_Explicit": 0, "Comparison_Arg2_Implicit": 0, "Contingency_Arg1_Explicit": 0, "Contingency_Arg1_Implicit": 0, "Contingency_Arg2_Explicit": 0, "Contingency_Arg2_Implicit": 0, "Expansion_Arg1_Explicit": 1, "Expansion_Arg1_Implicit": 1, "Expansion_Arg2_Explicit": 0, "Expansion_Arg2_Implicit": 1, "Temporal_Arg1_Explicit": 0, "Temporal_Arg1_Implicit": 0, "Temporal_Arg2_Explicit": 0, "Temporal_Arg2_Implicit": 0, "presence_positive_associations": 1, "presence_negative_associations": 1, "ratio_positive_associations": 0.425531914893617, "ratio_negative_associations": 0.10638297872340426, "between_forward_indicators": 0, "between_backwards_indicators": 0, "between_thesis_indicators": 0, "between_rebuttal_indicators": 0}, "8,5": {"is_a_relation": 1, "num_tokens": 39, "same_sentence": 0, "target_before_source": 1, "intro_or_conc": 0, "num_between": 2, "num_in_paragraph": 4, "share_noun": 0, "num_shared_nouns": 0, "first_or_last": 1, "component_forward_indicators": 1, "context_forward_indicators": 0, "component_backwards_indicators": 1, "context_backwards_indicators": 0, "component_thesis_indicators": 0, "context_thesis_indicators": 0, "component_rebuttal_indicators": 0, "context_rebuttal_indicators": 0, "CC": 2, "CD": 0, "DT": 2, "EX": 1, "FW": 0, "IN": 5, "JJ": 2, "JJR": 0, "JJS": 0, "LS": 0, "MD": 0, "NN": 8, "NNS": 4, "NNP": 2, "NNPS": 0, "PDT": 0, "POS": 0, "PRP": 1, "PRP$": 0, "RB": 0, "RBR": 0, "RBS": 1, "RP": 0, "SYM": 0, "TO": 0, "UH": 0, "VB": 0, "VBD": 0, "VBG": 0, "VBN": 1, "VBP": 3, "VBZ": 1, "WDT": 1, "WP": 0, "WP$": 0, "WRB": 1, "['PP', ['IN', 'NP']]": 3, "['S', ['NP', 'VP']]": 1, "['ROOT', ['S']]": 1, "['NP', ['NP', 'PP']]": 0, "['ADVP', ['RB']]": 0, "['NP', ['DT', 'NN']]": 0, "['NP', ['NNS']]": 0, "['S', ['VP']]": 0, "['VP', ['TO', 'VP']]": 0, "['SBAR', ['IN', 'S']]": 0, "['NP', ['NN']]": 0, "['NP', ['JJ', 'NNS']]": 0, "['VP', ['VB', 'NP']]": 0, "['NP', ['NN', 'NN']]": 0, "['VP', ['VBZ', 'SBAR']]": 0, "['NP', ['PRP']]": 0, "['S', ['NP', 'VP', '.']]": 0, "['NP', ['NP', 'CC', 'NP']]": 0, "['VP', ['VBZ', 'NP']]": 0, "['NP', ['PRP$', 'NN']]": 0, "['NP', ['NML', 'NN']]": 0, "['ADJP', ['RB', 'JJ']]": 0, "['VP', ['VBP', 'PP', 'SBAR']]": 0, "['NP', ['NN', 'NNS']]": 0, "['VP', ['VP', 'CC', 'VP']]": 0, "['VP', ['VB', 'NP', 'PP']]": 0, "['NP', ['NN', 'CC', 'NN']]": 0, "['VP', ['VBP', 'VP']]": 0, "['VP', ['VBP', 'NP']]": 0, "['NP', ['NP', 'SBAR']]": 0, "['WHNP', ['WDT']]": 0, "['NP', ['ADJP', 'NN']]": 0, "['S', ['S', ',', 'CC', 'S', '.']]": 0, "['NP', ['DT', 'JJ', 'CD']]": 0, "['S', ['PP', 'NP', 'VP']]": 0, "['NP', ['DT', 'NML', 'NN']]": 0, "['NML', ['ADVP']]": 0, "['ADVP', ['RBR']]": 0, "['S', ['NP', 'PP']]": 0, "['NP', ['NP', 'ADJP']]": 0, "['NML', ['JJ', 'NNS']]": 0, "['NP', ['CD', 'NN']]": 0, "['NP', ['NN', 'CC', 'NNS']]": 0, "['NP', ['NP', 'NNS']]": 0, "['NP', ['JJ', 'NNS', 'POS']]": 0, "['SBAR', ['IN', 'NN', 'S']]": 0, "['NP', ['PRP$', 'NN', 'CC', 'NN']]": 0, "['NML', ['NN', 'NN', 'CC', 'NN']]": 0, "['VP', ['VBP', 'ADVP', 'VP']]": 0, "['ADVP', ['RBR', 'CC', 'RBR']]": 0, "['VP', ['VBG', 'NP']]": 0, "['NP', ['NNS', 'NNS']]": 0, "['S', ['S', 'CC', 'S', 'CC', 'S', '.']]": 0, "['S', ['NP', ',', 'NP', 'VP']]": 0, "['VP', ['MD', 'VP']]": 0, "['VP', ['VB', 'ADVP']]": 0, "['NP', ['RB']]": 0, "['S', ['ADVP', 'NP', 'VP']]": 0, "['VP', ['VBP', 'RB', 'VP']]": 0, "['VP', ['VB', 'NP', 'S']]": 0, "['NP', ['DT', 'JJR']]": 0, "['VP', ['VBZ', 'S']]": 0, "['SBAR', ['WHADVP', 'S']]": 0, "['WHADVP', ['WRB']]": 0, "['NP', ['DT', 'ADJP', 'NN']]": 0, "['ADJP', ['RBS', 'JJ']]": 0, "['S', ['ADVP', ',', 'NP', 'ADVP', 'VP', '.']]": 0, "['NP', ['JJ', 'NN']]": 0, "['VP', ['VB', 'NP', 'ADVP', 'S', 'SBAR']]": 0, "['VP', ['VBG', 'CC', 'VBG']]": 0, "['S', ['S', ':', 'S', '.']]": 0, "['S', ['NP', 'ADVP', 'VP']]": 0, "['NP', ['DT']]": 0, "['VP', ['VBP', 'NP', 'NP']]": 0, "['NP', ['NNS', 'CC', 'NNS']]": 0, "['S', ['ADVP', ',', 'NP', 'VP', '.']]": 0, "['NP', ['EX']]": 0, "['NP', ['NP', ',', 'NP']]": 0, "['SBAR', ['WHPP', 'S']]": 0, "['WHPP', ['IN', 'WHNP']]": 0, "['VP', ['VBN', 'PP', ',', 'PP']]": 0, "['NP', ['JJ', 'NNS', 'CC', 'NNS']]": 0, "['NP', ['``', 'NNP', 'NNP', \"''\"]]": 0, "['S', ['S', ',', 'NP', 'VP', '.']]": 0, "['VP', ['VB', 'PRT']]": 0, "['PRT', ['RP']]": 0, "['VP', ['VBZ', 'ADJP', 'SBAR']]": 0, "['ADJP', ['JJ']]": 0, "['NP', ['NP', ',', 'NP', 'CC', 'NP']]": 0, "['VP', ['VBP', 'NP', 'PP']]": 0, "['NP', ['NP', 'JJ', 'NNS']]": 0, "['NP', ['NNS', 'POS']]": 0, "['NP', ['NP', 'VP']]": 0, "['NP', ['PDT', 'DT', 'NNS']]": 0, "['VP', ['VBN', 'ADVP', ',', 'ADVP', 'S']]": 0, "['ADJP', ['JJ', 'CC', 'JJ']]": 0, "['SBAR', ['WHNP', 'S']]": 0, "['VP', ['VBP', 'PP']]": 0, "Comparison_Arg1_Explicit": 0, "Comparison_Arg1_Implicit": 0, "Comparison_Arg2_Explicit": 0, "Comparison_Arg2_Implicit": 0, "Contingency_Arg1_Explicit": 0, "Contingency_Arg1_Implicit": 0, "Contingency_Arg2_Explicit": 0, "Contingency_Arg2_Implicit": 1, "Expansion_Arg1_Explicit": 0, "Expansion_Arg1_Implicit": 2, "Expansion_Arg2_Explicit": 0, "Expansion_Arg2_Implicit": 0, "Temporal_Arg1_Explicit": 0, "Temporal_Arg1_Implicit": 0, "Temporal_Arg2_Explicit": 0, "Temporal_Arg2_Implicit": 0, "presence_positive_associations": 1, "presence_negative_associations": 1, "ratio_positive_associations": 0.6923076923076923, "ratio_negative_associations": 0.07692307692307693, "between_forward_indicators": 0, "between_backwards_indicators": 0, "between_thesis_indicators": 0, "between_rebuttal_indicators": 0}, "8,6": {"is_a_relation": 0, "num_tokens": 43, "same_sentence": 0, "target_before_source": 1, "intro_or_conc": 0, "num_between": 1, "num_in_paragraph": 4, "share_noun": 0, "num_shared_nouns": 0, "first_or_last": 1, "component_forward_indicators": 0, "context_forward_indicators": 0, "component_backwards_indicators": 1, "context_backwards_indicators": 0, "component_thesis_indicators": 0, "context_thesis_indicators": 0, "component_rebuttal_indicators": 0, "context_rebuttal_indicators": 0, "CC": 2, "CD": 0, "DT": 1, "EX": 1, "FW": 0, "IN": 5, "JJ": 2, "JJR": 0, "JJS": 0, "LS": 0, "MD": 0, "NN": 6, "NNS": 5, "NNP": 2, "NNPS": 0, "PDT": 0, "POS": 0, "PRP": 1, "PRP$": 0, "RB": 3, "RBR": 0, "RBS": 0, "RP": 0, "SYM": 0, "TO": 1, "UH": 0, "VB": 2, "VBD": 0, "VBG": 2, "VBN": 1, "VBP": 3, "VBZ": 0, "WDT": 1, "WP": 0, "WP$": 0, "WRB": 0, "['PP', ['IN', 'NP']]": 0, "['S', ['NP', 'VP']]": 1, "['ROOT', ['S']]": 1, "['NP', ['NP', 'PP']]": 0, "['ADVP', ['RB']]": 1, "['NP', ['DT', 'NN']]": 0, "['NP', ['NNS']]": 1, "['S', ['VP']]": 0, "['VP', ['TO', 'VP']]": 0, "['SBAR', ['IN', 'S']]": 0, "['NP', ['NN']]": 0, "['NP', ['JJ', 'NNS']]": 0, "['VP', ['VB', 'NP']]": 0, "['NP', ['NN', 'NN']]": 0, "['VP', ['VBZ', 'SBAR']]": 0, "['NP', ['PRP']]": 0, "['S', ['NP', 'VP', '.']]": 0, "['NP', ['NP', 'CC', 'NP']]": 0, "['VP', ['VBZ', 'NP']]": 0, "['NP', ['PRP$', 'NN']]": 0, "['NP', ['NML', 'NN']]": 0, "['ADJP', ['RB', 'JJ']]": 0, "['VP', ['VBP', 'PP', 'SBAR']]": 0, "['NP', ['NN', 'NNS']]": 0, "['VP', ['VP', 'CC', 'VP']]": 0, "['VP', ['VB', 'NP', 'PP']]": 0, "['NP', ['NN', 'CC', 'NN']]": 0, "['VP', ['VBP', 'VP']]": 1, "['VP', ['VBP', 'NP']]": 0, "['NP', ['NP', 'SBAR']]": 0, "['WHNP', ['WDT']]": 0, "['NP', ['ADJP', 'NN']]": 0, "['S', ['S', ',', 'CC', 'S', '.']]": 0, "['NP', ['DT', 'JJ', 'CD']]": 0, "['S', ['PP', 'NP', 'VP']]": 0, "['NP', ['DT', 'NML', 'NN']]": 0, "['NML', ['ADVP']]": 0, "['ADVP', ['RBR']]": 0, "['S', ['NP', 'PP']]": 0, "['NP', ['NP', 'ADJP']]": 0, "['NML', ['JJ', 'NNS']]": 0, "['NP', ['CD', 'NN']]": 0, "['NP', ['NN', 'CC', 'NNS']]": 0, "['NP', ['NP', 'NNS']]": 0, "['NP', ['JJ', 'NNS', 'POS']]": 0, "['SBAR', ['IN', 'NN', 'S']]": 0, "['NP', ['PRP$', 'NN', 'CC', 'NN']]": 0, "['NML', ['NN', 'NN', 'CC', 'NN']]": 0, "['VP', ['VBP', 'ADVP', 'VP']]": 0, "['ADVP', ['RBR', 'CC', 'RBR']]": 0, "['VP', ['VBG', 'NP']]": 0, "['NP', ['NNS', 'NNS']]": 0, "['S', ['S', 'CC', 'S', 'CC', 'S', '.']]": 0, "['S', ['NP', ',', 'NP', 'VP']]": 0, "['VP', ['MD', 'VP']]": 0, "['VP', ['VB', 'ADVP']]": 0, "['NP', ['RB']]": 0, "['S', ['ADVP', 'NP', 'VP']]": 0, "['VP', ['VBP', 'RB', 'VP']]": 0, "['VP', ['VB', 'NP', 'S']]": 0, "['NP', ['DT', 'JJR']]": 0, "['VP', ['VBZ', 'S']]": 0, "['SBAR', ['WHADVP', 'S']]": 0, "['WHADVP', ['WRB']]": 0, "['NP', ['DT', 'ADJP', 'NN']]": 0, "['ADJP', ['RBS', 'JJ']]": 0, "['S', ['ADVP', ',', 'NP', 'ADVP', 'VP', '.']]": 0, "['NP', ['JJ', 'NN']]": 0, "['VP', ['VB', 'NP', 'ADVP', 'S', 'SBAR']]": 0, "['VP', ['VBG', 'CC', 'VBG']]": 0, "['S', ['S', ':', 'S', '.']]": 0, "['S', ['NP', 'ADVP', 'VP']]": 0, "['NP', ['DT']]": 0, "['VP', ['VBP', 'NP', 'NP']]": 0, "['NP', ['NNS', 'CC', 'NNS']]": 0, "['S', ['ADVP', ',', 'NP', 'VP', '.']]": 0, "['NP', ['EX']]": 0, "['NP', ['NP', ',', 'NP']]": 0, "['SBAR', ['WHPP', 'S']]": 0, "['WHPP', ['IN', 'WHNP']]": 0, "['VP', ['VBN', 'PP', ',', 'PP']]": 0, "['NP', ['JJ', 'NNS', 'CC', 'NNS']]": 0, "['NP', ['``', 'NNP', 'NNP', \"''\"]]": 0, "['S', ['S', ',', 'NP', 'VP', '.']]": 0, "['VP', ['VB', 'PRT']]": 0, "['PRT', ['RP']]": 0, "['VP', ['VBZ', 'ADJP', 'SBAR']]": 0, "['ADJP', ['JJ']]": 0, "['NP', ['NP', ',', 'NP', 'CC', 'NP']]": 0, "['VP', ['VBP', 'NP', 'PP']]": 0, "['NP', ['NP', 'JJ', 'NNS']]": 0, "['NP', ['NNS', 'POS']]": 0, "['NP', ['NP', 'VP']]": 0, "['NP', ['PDT', 'DT', 'NNS']]": 0, "['VP', ['VBN', 'ADVP', ',', 'ADVP', 'S']]": 0, "['ADJP', ['JJ', 'CC', 'JJ']]": 0, "['SBAR', ['WHNP', 'S']]": 0, "['VP', ['VBP', 'PP']]": 0, "Comparison_Arg1_Explicit": 0, "Comparison_Arg1_Implicit": 0, "Comparison_Arg2_Explicit": 0, "Comparison_Arg2_Implicit": 0, "Contingency_Arg1_Explicit": 0, "Contingency_Arg1_Implicit": 0, "Contingency_Arg2_Explicit": 0, "Contingency_Arg2_Implicit": 0, "Expansion_Arg1_Explicit": 0, "Expansion_Arg1_Implicit": 2, "Expansion_Arg2_Explicit": 0, "Expansion_Arg2_Implicit": 1, "Temporal_Arg1_Explicit": 0, "Temporal_Arg1_Implicit": 0, "Temporal_Arg2_Explicit": 0, "Temporal_Arg2_Implicit": 0, "presence_positive_associations": 1, "presence_negative_associations": 1, "ratio_positive_associations": 0.627906976744186, "ratio_negative_associations": 0.06976744186046512, "between_forward_indicators": 0, "between_backwards_indicators": 0, "between_thesis_indicators": 0, "between_rebuttal_indicators": 0}, "8,7": {"is_a_relation": 0, "num_tokens": 47, "same_sentence": 0, "target_before_source": 1, "intro_or_conc": 0, "num_between": 0, "num_in_paragraph": 4, "share_noun": 1, "num_shared_nouns": 1, "first_or_last": 1, "component_forward_indicators": 0, "context_forward_indicators": 0, "component_backwards_indicators": 1, "context_backwards_indicators": 0, "component_thesis_indicators": 0, "context_thesis_indicators": 0, "component_rebuttal_indicators": 0, "context_rebuttal_indicators": 0, "CC": 2, "CD": 0, "DT": 2, "EX": 1, "FW": 0, "IN": 8, "JJ": 1, "JJR": 0, "JJS": 0, "LS": 0, "MD": 0, "NN": 8, "NNS": 10, "NNP": 2, "NNPS": 0, "PDT": 0, "POS": 0, "PRP": 0, "PRP$": 0, "RB": 1, "RBR": 0, "RBS": 0, "RP": 0, "SYM": 0, "TO": 0, "UH": 0, "VB": 0, "VBD": 0, "VBG": 0, "VBN": 1, "VBP": 4, "VBZ": 1, "WDT": 1, "WP": 0, "WP$": 0, "WRB": 0, "['PP', ['IN', 'NP']]": 3, "['S', ['NP', 'VP']]": 1, "['ROOT', ['S']]": 1, "['NP', ['NP', 'PP']]": 1, "['ADVP', ['RB']]": 1, "['NP', ['DT', 'NN']]": 0, "['NP', ['NNS']]": 1, "['S', ['VP']]": 0, "['VP', ['TO', 'VP']]": 0, "['SBAR', ['IN', 'S']]": 0, "['NP', ['NN']]": 1, "['NP', ['JJ', 'NNS']]": 0, "['VP', ['VB', 'NP']]": 0, "['NP', ['NN', 'NN']]": 1, "['VP', ['VBZ', 'SBAR']]": 0, "['NP', ['PRP']]": 0, "['S', ['NP', 'VP', '.']]": 0, "['NP', ['NP', 'CC', 'NP']]": 0, "['VP', ['VBZ', 'NP']]": 0, "['NP', ['PRP$', 'NN']]": 0, "['NP', ['NML', 'NN']]": 0, "['ADJP', ['RB', 'JJ']]": 0, "['VP', ['VBP', 'PP', 'SBAR']]": 0, "['NP', ['NN', 'NNS']]": 0, "['VP', ['VP', 'CC', 'VP']]": 0, "['VP', ['VB', 'NP', 'PP']]": 0, "['NP', ['NN', 'CC', 'NN']]": 0, "['VP', ['VBP', 'VP']]": 0, "['VP', ['VBP', 'NP']]": 1, "['NP', ['NP', 'SBAR']]": 0, "['WHNP', ['WDT']]": 0, "['NP', ['ADJP', 'NN']]": 0, "['S', ['S', ',', 'CC', 'S', '.']]": 0, "['NP', ['DT', 'JJ', 'CD']]": 0, "['S', ['PP', 'NP', 'VP']]": 0, "['NP', ['DT', 'NML', 'NN']]": 0, "['NML', ['ADVP']]": 0, "['ADVP', ['RBR']]": 0, "['S', ['NP', 'PP']]": 0, "['NP', ['NP', 'ADJP']]": 0, "['NML', ['JJ', 'NNS']]": 0, "['NP', ['CD', 'NN']]": 0, "['NP', ['NN', 'CC', 'NNS']]": 0, "['NP', ['NP', 'NNS']]": 0, "['NP', ['JJ', 'NNS', 'POS']]": 0, "['SBAR', ['IN', 'NN', 'S']]": 0, "['NP', ['PRP$', 'NN', 'CC', 'NN']]": 0, "['NML', ['NN', 'NN', 'CC', 'NN']]": 0, "['VP', ['VBP', 'ADVP', 'VP']]": 0, "['ADVP', ['RBR', 'CC', 'RBR']]": 0, "['VP', ['VBG', 'NP']]": 0, "['NP', ['NNS', 'NNS']]": 0, "['S', ['S', 'CC', 'S', 'CC', 'S', '.']]": 0, "['S', ['NP', ',', 'NP', 'VP']]": 0, "['VP', ['MD', 'VP']]": 0, "['VP', ['VB', 'ADVP']]": 0, "['NP', ['RB']]": 0, "['S', ['ADVP', 'NP', 'VP']]": 0, "['VP', ['VBP', 'RB', 'VP']]": 0, "['VP', ['VB', 'NP', 'S']]": 0, "['NP', ['DT', 'JJR']]": 0, "['VP', ['VBZ', 'S']]": 0, "['SBAR', ['WHADVP', 'S']]": 0, "['WHADVP', ['WRB']]": 0, "['NP', ['DT', 'ADJP', 'NN']]": 0, "['ADJP', ['RBS', 'JJ']]": 0, "['S', ['ADVP', ',', 'NP', 'ADVP', 'VP', '.']]": 0, "['NP', ['JJ', 'NN']]": 0, "['VP', ['VB', 'NP', 'ADVP', 'S', 'SBAR']]": 0, "['VP', ['VBG', 'CC', 'VBG']]": 0, "['S', ['S', ':', 'S', '.']]": 0, "['S', ['NP', 'ADVP', 'VP']]": 0, "['NP', ['DT']]": 0, "['VP', ['VBP', 'NP', 'NP']]": 0, "['NP', ['NNS', 'CC', 'NNS']]": 0, "['S', ['ADVP', ',', 'NP', 'VP', '.']]": 0, "['NP', ['EX']]": 0, "['NP', ['NP', ',', 'NP']]": 0, "['SBAR', ['WHPP', 'S']]": 0, "['WHPP', ['IN', 'WHNP']]": 0, "['VP', ['VBN', 'PP', ',', 'PP']]": 0, "['NP', ['JJ', 'NNS', 'CC', 'NNS']]": 0, "['NP', ['``', 'NNP', 'NNP', \"''\"]]": 0, "['S', ['S', ',', 'NP', 'VP', '.']]": 0, "['VP', ['VB', 'PRT']]": 0, "['PRT', ['RP']]": 0, "['VP', ['VBZ', 'ADJP', 'SBAR']]": 0, "['ADJP', ['JJ']]": 0, "['NP', ['NP', ',', 'NP', 'CC', 'NP']]": 0, "['VP', ['VBP', 'NP', 'PP']]": 0, "['NP', ['NP', 'JJ', 'NNS']]": 0, "['NP', ['NNS', 'POS']]": 0, "['NP', ['NP', 'VP']]": 0, "['NP', ['PDT', 'DT', 'NNS']]": 0, "['VP', ['VBN', 'ADVP', ',', 'ADVP', 'S']]": 0, "['ADJP', ['JJ', 'CC', 'JJ']]": 0, "['SBAR', ['WHNP', 'S']]": 0, "['VP', ['VBP', 'PP']]": 0, "Comparison_Arg1_Explicit": 0, "Comparison_Arg1_Implicit": 0, "Comparison_Arg2_Explicit": 0, "Comparison_Arg2_Implicit": 0, "Contingency_Arg1_Explicit": 0, "Contingency_Arg1_Implicit": 0, "Contingency_Arg2_Explicit": 0, "Contingency_Arg2_Implicit": 0, "Expansion_Arg1_Explicit": 1, "Expansion_Arg1_Implicit": 1, "Expansion_Arg2_Explicit": 0, "Expansion_Arg2_Implicit": 1, "Temporal_Arg1_Explicit": 0, "Temporal_Arg1_Implicit": 0, "Temporal_Arg2_Explicit": 0, "Temporal_Arg2_Implicit": 0, "presence_positive_associations": 1, "presence_negative_associations": 1, "ratio_positive_associations": 0.574468085106383, "ratio_negative_associations": 0.06382978723404255, "between_forward_indicators": 0, "between_backwards_indicators": 0, "between_thesis_indicators": 0, "between_rebuttal_indicators": 0}}