{"1,2": {"is_a_relation": 0, "num_tokens": 42, "same_sentence": 0, "target_before_source": 0, "intro_or_conc": 0, "num_between": 0, "num_in_paragraph": 2, "share_noun": 1, "num_shared_nouns": 1, "first_or_last": 1, "component_forward_indicators": 1, "context_forward_indicators": 0, "component_backwards_indicators": 1, "context_backwards_indicators": 0, "component_thesis_indicators": 0, "context_thesis_indicators": 0, "component_rebuttal_indicators": 0, "context_rebuttal_indicators": 0, "CC": 2, "CD": 0, "DT": 4, "EX": 0, "FW": 0, "IN": 9, "JJ": 5, "JJR": 0, "JJS": 0, "LS": 0, "MD": 0, "NN": 9, "NNS": 4, "NNP": 0, "NNPS": 0, "PDT": 0, "POS": 0, "PRP": 1, "PRP$": 2, "RB": 0, "RBR": 0, "RBS": 0, "RP": 0, "SYM": 0, "TO": 1, "UH": 0, "VB": 2, "VBD": 1, "VBG": 0, "VBN": 1, "VBP": 1, "VBZ": 0, "WDT": 0, "WP": 0, "WP$": 0, "WRB": 0, "['PP', ['IN', 'NP']]": 4, "['NP', ['NP', 'PP']]": 2, "['NP', ['NN']]": 1, "['NP', ['DT', 'NN']]": 1, "['S', ['VP']]": 0, "['NP', ['NNS']]": 0, "['ROOT', ['S']]": 1, "['NP', ['PRP']]": 0, "['NP', ['JJ', 'NN']]": 0, "['NP', ['DT', 'NNS']]": 0, "['S', ['NP', 'VP']]": 0, "['ADVP', ['RB']]": 0, "['NP', ['DT', 'JJ', 'NN']]": 0, "['VP', ['VBP', 'SBAR']]": 0, "['SBAR', ['IN', 'S']]": 0, "['NP', ['JJ', 'NNS']]": 0, "['NP', ['NP', 'SBAR']]": 0, "['SBAR', ['WHNP', 'S']]": 0, "['S', ['NP', 'VP', '.']]": 1, "['VP', ['TO', 'VP']]": 0, "['VP', ['VB', 'NP', 'PP', 'PP']]": 0, "['NP', ['PRP$', 'NN']]": 0, "['VP', ['VBG', 'NP']]": 0, "['VP', ['MD', 'VP']]": 0, "['VP', ['VB', 'NP', 'PP']]": 0, "['S', ['PP', ',', 'NP', 'VP', '.']]": 0, "['ROOT', ['FRAG']]": 0, "['FRAG', ['ADVP', ',', 'NP', 'PP', '.']]": 0, "['NP', ['NN', 'NN', 'NN']]": 0, "['NP', ['NN', 'NNS']]": 0, "['PP', ['IN', 'IN', 'NP']]": 0, "['WHNP', ['WDT']]": 0, "['VP', ['VBZ', 'NP']]": 0, "['VP', ['VBP', 'S']]": 0, "['NP', ['ADJP', 'NNS']]": 0, "['ADJP', ['JJ', 'CC', 'JJ']]": 0, "['VP', ['VP', 'CC', 'VP']]": 0, "['VP', ['VBD', 'NP', 'PP']]": 0, "['NP', ['PRP$', 'VBN', 'NN']]": 0, "['VP', ['VB', 'S']]": 0, "['S', ['NP', 'ADJP']]": 0, "['ADJP', ['JJ', 'PP']]": 0, "['S', ['NP', ',', 'VP', '.']]": 0, "['NP', ['DT']]": 0, "['WHNP', ['WP']]": 0, "['VP', ['VBP']]": 0, "['VP', ['VBP', 'ADVP', 'PP']]": 0, "['S', ['S', 'CC', 'S', '.']]": 0, "['S', ['S', ',', 'NP', 'VP']]": 0, "['NP', ['JJR', 'NN']]": 0, "['NP', ['JJ', 'JJ', 'NNS']]": 0, "['VP', ['VBZ', 'PP']]": 0, "['PP', ['IN', 'S']]": 0, "['NP', ['NP', 'PP', 'PP']]": 0, "['NP', ['UCP', 'NNS']]": 0, "['UCP', ['JJ', 'CC', 'JJ']]": 0, "['VP', ['VB', 'VP']]": 0, "['VP', ['VBN', 'NP', 'PP', 'S']]": 0, "['NP', ['NP', 'VP']]": 0, "['NP', ['DT', 'NNS', 'CC', 'NNS']]": 0, "['VP', ['VBN', 'PP']]": 0, "['VP', ['MD', 'ADVP', 'VP']]": 0, "['NP', ['DT', 'NN', 'NN']]": 0, "Comparison_Arg1_Explicit": 0, "Comparison_Arg1_Implicit": 0, "Comparison_Arg2_Explicit": 0, "Comparison_Arg2_Implicit": 0, "Contingency_Arg1_Explicit": 0, "Contingency_Arg1_Implicit": 0, "Contingency_Arg2_Explicit": 0, "Contingency_Arg2_Implicit": 0, "Expansion_Arg1_Explicit": 0, "Expansion_Arg1_Implicit": 2, "Expansion_Arg2_Explicit": 0, "Expansion_Arg2_Implicit": 2, "Temporal_Arg1_Explicit": 0, "Temporal_Arg1_Implicit": 0, "Temporal_Arg2_Explicit": 0, "Temporal_Arg2_Implicit": 0, "presence_positive_associations": 1, "presence_negative_associations": 1, "ratio_positive_associations": 0.6904761904761905, "ratio_negative_associations": 0.19047619047619047, "between_forward_indicators": 0, "between_backwards_indicators": 0, "between_thesis_indicators": 0, "between_rebuttal_indicators": 0}, "2,1": {"is_a_relation": 1, "num_tokens": 42, "same_sentence": 0, "target_before_source": 1, "intro_or_conc": 0, "num_between": 0, "num_in_paragraph": 2, "share_noun": 1, "num_shared_nouns": 1, "first_or_last": 1, "component_forward_indicators": 1, "context_forward_indicators": 0, "component_backwards_indicators": 1, "context_backwards_indicators": 0, "component_thesis_indicators": 0, "context_thesis_indicators": 0, "component_rebuttal_indicators": 0, "context_rebuttal_indicators": 0, "CC": 2, "CD": 0, "DT": 4, "EX": 0, "FW": 0, "IN": 9, "JJ": 5, "JJR": 0, "JJS": 0, "LS": 0, "MD": 0, "NN": 9, "NNS": 4, "NNP": 0, "NNPS": 0, "PDT": 0, "POS": 0, "PRP": 1, "PRP$": 2, "RB": 0, "RBR": 0, "RBS": 0, "RP": 0, "SYM": 0, "TO": 1, "UH": 0, "VB": 2, "VBD": 1, "VBG": 0, "VBN": 1, "VBP": 1, "VBZ": 0, "WDT": 0, "WP": 0, "WP$": 0, "WRB": 0, "['PP', ['IN', 'NP']]": 5, "['NP', ['NP', 'PP']]": 3, "['NP', ['NN']]": 2, "['NP', ['DT', 'NN']]": 2, "['S', ['VP']]": 0, "['NP', ['NNS']]": 0, "['ROOT', ['S']]": 1, "['NP', ['PRP']]": 0, "['NP', ['JJ', 'NN']]": 0, "['NP', ['DT', 'NNS']]": 0, "['S', ['NP', 'VP']]": 0, "['ADVP', ['RB']]": 0, "['NP', ['DT', 'JJ', 'NN']]": 0, "['VP', ['VBP', 'SBAR']]": 0, "['SBAR', ['IN', 'S']]": 0, "['NP', ['JJ', 'NNS']]": 0, "['NP', ['NP', 'SBAR']]": 0, "['SBAR', ['WHNP', 'S']]": 0, "['S', ['NP', 'VP', '.']]": 1, "['VP', ['TO', 'VP']]": 0, "['VP', ['VB', 'NP', 'PP', 'PP']]": 0, "['NP', ['PRP$', 'NN']]": 0, "['VP', ['VBG', 'NP']]": 0, "['VP', ['MD', 'VP']]": 0, "['VP', ['VB', 'NP', 'PP']]": 0, "['S', ['PP', ',', 'NP', 'VP', '.']]": 0, "['ROOT', ['FRAG']]": 0, "['FRAG', ['ADVP', ',', 'NP', 'PP', '.']]": 0, "['NP', ['NN', 'NN', 'NN']]": 0, "['NP', ['NN', 'NNS']]": 0, "['PP', ['IN', 'IN', 'NP']]": 0, "['WHNP', ['WDT']]": 0, "['VP', ['VBZ', 'NP']]": 0, "['VP', ['VBP', 'S']]": 0, "['NP', ['ADJP', 'NNS']]": 0, "['ADJP', ['JJ', 'CC', 'JJ']]": 0, "['VP', ['VP', 'CC', 'VP']]": 0, "['VP', ['VBD', 'NP', 'PP']]": 0, "['NP', ['PRP$', 'VBN', 'NN']]": 0, "['VP', ['VB', 'S']]": 0, "['S', ['NP', 'ADJP']]": 0, "['ADJP', ['JJ', 'PP']]": 0, "['S', ['NP', ',', 'VP', '.']]": 0, "['NP', ['DT']]": 0, "['WHNP', ['WP']]": 0, "['VP', ['VBP']]": 0, "['VP', ['VBP', 'ADVP', 'PP']]": 0, "['S', ['S', 'CC', 'S', '.']]": 0, "['S', ['S', ',', 'NP', 'VP']]": 0, "['NP', ['JJR', 'NN']]": 0, "['NP', ['JJ', 'JJ', 'NNS']]": 0, "['VP', ['VBZ', 'PP']]": 0, "['PP', ['IN', 'S']]": 0, "['NP', ['NP', 'PP', 'PP']]": 0, "['NP', ['UCP', 'NNS']]": 0, "['UCP', ['JJ', 'CC', 'JJ']]": 0, "['VP', ['VB', 'VP']]": 0, "['VP', ['VBN', 'NP', 'PP', 'S']]": 0, "['NP', ['NP', 'VP']]": 0, "['NP', ['DT', 'NNS', 'CC', 'NNS']]": 0, "['VP', ['VBN', 'PP']]": 0, "['VP', ['MD', 'ADVP', 'VP']]": 0, "['NP', ['DT', 'NN', 'NN']]": 0, "Comparison_Arg1_Explicit": 0, "Comparison_Arg1_Implicit": 0, "Comparison_Arg2_Explicit": 0, "Comparison_Arg2_Implicit": 0, "Contingency_Arg1_Explicit": 0, "Contingency_Arg1_Implicit": 0, "Contingency_Arg2_Explicit": 0, "Contingency_Arg2_Implicit": 0, "Expansion_Arg1_Explicit": 0, "Expansion_Arg1_Implicit": 2, "Expansion_Arg2_Explicit": 0, "Expansion_Arg2_Implicit": 2, "Temporal_Arg1_Explicit": 0, "Temporal_Arg1_Implicit": 0, "Temporal_Arg2_Explicit": 0, "Temporal_Arg2_Implicit": 0, "presence_positive_associations": 1, "presence_negative_associations": 1, "ratio_positive_associations": 0.8571428571428571, "ratio_negative_associations": 0.14285714285714285, "between_forward_indicators": 0, "between_backwards_indicators": 0, "between_thesis_indicators": 0, "between_rebuttal_indicators": 0}, "3,4": {"is_a_relation": 0, "num_tokens": 44, "same_sentence": 0, "target_before_source": 0, "intro_or_conc": 0, "num_between": 0, "num_in_paragraph": 3, "share_noun": 1, "num_shared_nouns": 2, "first_or_last": 1, "component_forward_indicators": 1, "context_forward_indicators": 0, "component_backwards_indicators": 0, "context_backwards_indicators": 0, "component_thesis_indicators": 0, "context_thesis_indicators": 0, "component_rebuttal_indicators": 1, "context_rebuttal_indicators": 0, "CC": 2, "CD": 0, "DT": 5, "EX": 0, "FW": 0, "IN": 8, "JJ": 7, "JJR": 1, "JJS": 0, "LS": 0, "MD": 1, "NN": 8, "NNS": 4, "NNP": 0, "NNPS": 0, "PDT": 0, "POS": 0, "PRP": 1, "PRP$": 0, "RB": 1, "RBR": 0, "RBS": 0, "RP": 0, "SYM": 0, "TO": 0, "UH": 0, "VB": 1, "VBD": 0, "VBG": 2, "VBN": 0, "VBP": 1, "VBZ": 1, "WDT": 0, "WP": 0, "WP$": 0, "WRB": 0, "['PP', ['IN', 'NP']]": 3, "['NP', ['NP', 'PP']]": 2, "['NP', ['NN']]": 1, "['NP', ['DT', 'NN']]": 1, "['S', ['VP']]": 1, "['NP', ['NNS']]": 0, "['ROOT', ['S']]": 1, "['NP', ['PRP']]": 0, "['NP', ['JJ', 'NN']]": 0, "['NP', ['DT', 'NNS']]": 0, "['S', ['NP', 'VP']]": 1, "['ADVP', ['RB']]": 0, "['NP', ['DT', 'JJ', 'NN']]": 1, "['VP', ['VBP', 'SBAR']]": 0, "['SBAR', ['IN', 'S']]": 0, "['NP', ['JJ', 'NNS']]": 0, "['NP', ['NP', 'SBAR']]": 0, "['SBAR', ['WHNP', 'S']]": 0, "['S', ['NP', 'VP', '.']]": 0, "['VP', ['TO', 'VP']]": 0, "['VP', ['VB', 'NP', 'PP', 'PP']]": 0, "['NP', ['PRP$', 'NN']]": 0, "['VP', ['VBG', 'NP']]": 0, "['VP', ['MD', 'VP']]": 0, "['VP', ['VB', 'NP', 'PP']]": 0, "['S', ['PP', ',', 'NP', 'VP', '.']]": 0, "['ROOT', ['FRAG']]": 0, "['FRAG', ['ADVP', ',', 'NP', 'PP', '.']]": 0, "['NP', ['NN', 'NN', 'NN']]": 0, "['NP', ['NN', 'NNS']]": 0, "['PP', ['IN', 'IN', 'NP']]": 0, "['WHNP', ['WDT']]": 0, "['VP', ['VBZ', 'NP']]": 0, "['VP', ['VBP', 'S']]": 0, "['NP', ['ADJP', 'NNS']]": 0, "['ADJP', ['JJ', 'CC', 'JJ']]": 0, "['VP', ['VP', 'CC', 'VP']]": 0, "['VP', ['VBD', 'NP', 'PP']]": 0, "['NP', ['PRP$', 'VBN', 'NN']]": 0, "['VP', ['VB', 'S']]": 0, "['S', ['NP', 'ADJP']]": 0, "['ADJP', ['JJ', 'PP']]": 0, "['S', ['NP', ',', 'VP', '.']]": 0, "['NP', ['DT']]": 0, "['WHNP', ['WP']]": 0, "['VP', ['VBP']]": 0, "['VP', ['VBP', 'ADVP', 'PP']]": 0, "['S', ['S', 'CC', 'S', '.']]": 0, "['S', ['S', ',', 'NP', 'VP']]": 0, "['NP', ['JJR', 'NN']]": 0, "['NP', ['JJ', 'JJ', 'NNS']]": 0, "['VP', ['VBZ', 'PP']]": 0, "['PP', ['IN', 'S']]": 0, "['NP', ['NP', 'PP', 'PP']]": 0, "['NP', ['UCP', 'NNS']]": 0, "['UCP', ['JJ', 'CC', 'JJ']]": 0, "['VP', ['VB', 'VP']]": 0, "['VP', ['VBN', 'NP', 'PP', 'S']]": 0, "['NP', ['NP', 'VP']]": 0, "['NP', ['DT', 'NNS', 'CC', 'NNS']]": 0, "['VP', ['VBN', 'PP']]": 0, "['VP', ['MD', 'ADVP', 'VP']]": 0, "['NP', ['DT', 'NN', 'NN']]": 0, "Comparison_Arg1_Explicit": 0, "Comparison_Arg1_Implicit": 0, "Comparison_Arg2_Explicit": 0, "Comparison_Arg2_Implicit": 0, "Contingency_Arg1_Explicit": 0, "Contingency_Arg1_Implicit": 0, "Contingency_Arg2_Explicit": 0, "Contingency_Arg2_Implicit": 0, "Expansion_Arg1_Explicit": 1, "Expansion_Arg1_Implicit": 1, "Expansion_Arg2_Explicit": 0, "Expansion_Arg2_Implicit": 2, "Temporal_Arg1_Explicit": 0, "Temporal_Arg1_Implicit": 0, "Temporal_Arg2_Explicit": 0, "Temporal_Arg2_Implicit": 0, "presence_positive_associations": 1, "presence_negative_associations": 1, "ratio_positive_associations": 0.5227272727272727, "ratio_negative_associations": 0.06818181818181818, "between_forward_indicators": 0, "between_backwards_indicators": 0, "between_thesis_indicators": 0, "between_rebuttal_indicators": 0}, "3,5": {"is_a_relation": 0, "num_tokens": 40, "same_sentence": 0, "target_before_source": 0, "intro_or_conc": 0, "num_between": 1, "num_in_paragraph": 3, "share_noun": 1, "num_shared_nouns": 1, "first_or_last": 1, "component_forward_indicators": 0, "context_forward_indicators": 0, "component_backwards_indicators": 0, "context_backwards_indicators": 0, "component_thesis_indicators": 0, "context_thesis_indicators": 0, "component_rebuttal_indicators": 1, "context_rebuttal_indicators": 0, "CC": 1, "CD": 0, "DT": 5, "EX": 0, "FW": 0, "IN": 8, "JJ": 3, "JJR": 0, "JJS": 0, "LS": 0, "MD": 1, "NN": 7, "NNS": 5, "NNP": 0, "NNPS": 0, "PDT": 0, "POS": 0, "PRP": 1, "PRP$": 1, "RB": 1, "RBR": 0, "RBS": 0, "RP": 0, "SYM": 0, "TO": 1, "UH": 0, "VB": 2, "VBD": 0, "VBG": 0, "VBN": 2, "VBP": 2, "VBZ": 0, "WDT": 0, "WP": 0, "WP$": 0, "WRB": 0, "['PP', ['IN', 'NP']]": 3, "['NP', ['NP', 'PP']]": 2, "['NP', ['NN']]": 1, "['NP', ['DT', 'NN']]": 1, "['S', ['VP']]": 1, "['NP', ['NNS']]": 0, "['ROOT', ['S']]": 1, "['NP', ['PRP']]": 0, "['NP', ['JJ', 'NN']]": 0, "['NP', ['DT', 'NNS']]": 0, "['S', ['NP', 'VP']]": 1, "['ADVP', ['RB']]": 0, "['NP', ['DT', 'JJ', 'NN']]": 0, "['VP', ['VBP', 'SBAR']]": 1, "['SBAR', ['IN', 'S']]": 1, "['NP', ['JJ', 'NNS']]": 1, "['NP', ['NP', 'SBAR']]": 0, "['SBAR', ['WHNP', 'S']]": 0, "['S', ['NP', 'VP', '.']]": 0, "['VP', ['TO', 'VP']]": 0, "['VP', ['VB', 'NP', 'PP', 'PP']]": 0, "['NP', ['PRP$', 'NN']]": 0, "['VP', ['VBG', 'NP']]": 0, "['VP', ['MD', 'VP']]": 0, "['VP', ['VB', 'NP', 'PP']]": 0, "['S', ['PP', ',', 'NP', 'VP', '.']]": 0, "['ROOT', ['FRAG']]": 0, "['FRAG', ['ADVP', ',', 'NP', 'PP', '.']]": 0, "['NP', ['NN', 'NN', 'NN']]": 0, "['NP', ['NN', 'NNS']]": 0, "['PP', ['IN', 'IN', 'NP']]": 0, "['WHNP', ['WDT']]": 0, "['VP', ['VBZ', 'NP']]": 0, "['VP', ['VBP', 'S']]": 0, "['NP', ['ADJP', 'NNS']]": 0, "['ADJP', ['JJ', 'CC', 'JJ']]": 0, "['VP', ['VP', 'CC', 'VP']]": 0, "['VP', ['VBD', 'NP', 'PP']]": 0, "['NP', ['PRP$', 'VBN', 'NN']]": 0, "['VP', ['VB', 'S']]": 0, "['S', ['NP', 'ADJP']]": 0, "['ADJP', ['JJ', 'PP']]": 0, "['S', ['NP', ',', 'VP', '.']]": 0, "['NP', ['DT']]": 0, "['WHNP', ['WP']]": 0, "['VP', ['VBP']]": 0, "['VP', ['VBP', 'ADVP', 'PP']]": 0, "['S', ['S', 'CC', 'S', '.']]": 0, "['S', ['S', ',', 'NP', 'VP']]": 0, "['NP', ['JJR', 'NN']]": 0, "['NP', ['JJ', 'JJ', 'NNS']]": 0, "['VP', ['VBZ', 'PP']]": 0, "['PP', ['IN', 'S']]": 0, "['NP', ['NP', 'PP', 'PP']]": 0, "['NP', ['UCP', 'NNS']]": 0, "['UCP', ['JJ', 'CC', 'JJ']]": 0, "['VP', ['VB', 'VP']]": 0, "['VP', ['VBN', 'NP', 'PP', 'S']]": 0, "['NP', ['NP', 'VP']]": 0, "['NP', ['DT', 'NNS', 'CC', 'NNS']]": 0, "['VP', ['VBN', 'PP']]": 0, "['VP', ['MD', 'ADVP', 'VP']]": 0, "['NP', ['DT', 'NN', 'NN']]": 0, "Comparison_Arg1_Explicit": 0, "Comparison_Arg1_Implicit": 0, "Comparison_Arg2_Explicit": 0, "Comparison_Arg2_Implicit": 0, "Contingency_Arg1_Explicit": 0, "Contingency_Arg1_Implicit": 0, "Contingency_Arg2_Explicit": 0, "Contingency_Arg2_Implicit": 0, "Expansion_Arg1_Explicit": 1, "Expansion_Arg1_Implicit": 1, "Expansion_Arg2_Explicit": 1, "Expansion_Arg2_Implicit": 1, "Temporal_Arg1_Explicit": 0, "Temporal_Arg1_Implicit": 0, "Temporal_Arg2_Explicit": 0, "Temporal_Arg2_Implicit": 0, "presence_positive_associations": 1, "presence_negative_associations": 1, "ratio_positive_associations": 0.575, "ratio_negative_associations": 0.075, "between_forward_indicators": 1, "between_backwards_indicators": 0, "between_thesis_indicators": 0, "between_rebuttal_indicators": 0}, "4,3": {"is_a_relation": 1, "num_tokens": 44, "same_sentence": 0, "target_before_source": 1, "intro_or_conc": 0, "num_between": 0, "num_in_paragraph": 3, "share_noun": 1, "num_shared_nouns": 3, "first_or_last": 1, "component_forward_indicators": 1, "context_forward_indicators": 0, "component_backwards_indicators": 0, "context_backwards_indicators": 0, "component_thesis_indicators": 0, "context_thesis_indicators": 0, "component_rebuttal_indicators": 1, "context_rebuttal_indicators": 0, "CC": 2, "CD": 0, "DT": 5, "EX": 0, "FW": 0, "IN": 8, "JJ": 7, "JJR": 1, "JJS": 0, "LS": 0, "MD": 1, "NN": 8, "NNS": 4, "NNP": 0, "NNPS": 0, "PDT": 0, "POS": 0, "PRP": 1, "PRP$": 0, "RB": 1, "RBR": 0, "RBS": 0, "RP": 0, "SYM": 0, "TO": 0, "UH": 0, "VB": 1, "VBD": 0, "VBG": 2, "VBN": 0, "VBP": 1, "VBZ": 1, "WDT": 0, "WP": 0, "WP$": 0, "WRB": 0, "['PP', ['IN', 'NP']]": 4, "['NP', ['NP', 'PP']]": 1, "['NP', ['NN']]": 1, "['NP', ['DT', 'NN']]": 2, "['S', ['VP']]": 2, "['NP', ['NNS']]": 0, "['ROOT', ['S']]": 1, "['NP', ['PRP']]": 0, "['NP', ['JJ', 'NN']]": 0, "['NP', ['DT', 'NNS']]": 0, "['S', ['NP', 'VP']]": 1, "['ADVP', ['RB']]": 0, "['NP', ['DT', 'JJ', 'NN']]": 1, "['VP', ['VBP', 'SBAR']]": 0, "['SBAR', ['IN', 'S']]": 0, "['NP', ['JJ', 'NNS']]": 0, "['NP', ['NP', 'SBAR']]": 0, "['SBAR', ['WHNP', 'S']]": 0, "['S', ['NP', 'VP', '.']]": 0, "['VP', ['TO', 'VP']]": 0, "['VP', ['VB', 'NP', 'PP', 'PP']]": 0, "['NP', ['PRP$', 'NN']]": 0, "['VP', ['VBG', 'NP']]": 0, "['VP', ['MD', 'VP']]": 0, "['VP', ['VB', 'NP', 'PP']]": 0, "['S', ['PP', ',', 'NP', 'VP', '.']]": 0, "['ROOT', ['FRAG']]": 0, "['FRAG', ['ADVP', ',', 'NP', 'PP', '.']]": 0, "['NP', ['NN', 'NN', 'NN']]": 0, "['NP', ['NN', 'NNS']]": 0, "['PP', ['IN', 'IN', 'NP']]": 0, "['WHNP', ['WDT']]": 0, "['VP', ['VBZ', 'NP']]": 0, "['VP', ['VBP', 'S']]": 0, "['NP', ['ADJP', 'NNS']]": 0, "['ADJP', ['JJ', 'CC', 'JJ']]": 0, "['VP', ['VP', 'CC', 'VP']]": 0, "['VP', ['VBD', 'NP', 'PP']]": 0, "['NP', ['PRP$', 'VBN', 'NN']]": 0, "['VP', ['VB', 'S']]": 0, "['S', ['NP', 'ADJP']]": 0, "['ADJP', ['JJ', 'PP']]": 0, "['S', ['NP', ',', 'VP', '.']]": 0, "['NP', ['DT']]": 0, "['WHNP', ['WP']]": 0, "['VP', ['VBP']]": 0, "['VP', ['VBP', 'ADVP', 'PP']]": 0, "['S', ['S', 'CC', 'S', '.']]": 0, "['S', ['S', ',', 'NP', 'VP']]": 0, "['NP', ['JJR', 'NN']]": 0, "['NP', ['JJ', 'JJ', 'NNS']]": 0, "['VP', ['VBZ', 'PP']]": 0, "['PP', ['IN', 'S']]": 0, "['NP', ['NP', 'PP', 'PP']]": 0, "['NP', ['UCP', 'NNS']]": 0, "['UCP', ['JJ', 'CC', 'JJ']]": 0, "['VP', ['VB', 'VP']]": 0, "['VP', ['VBN', 'NP', 'PP', 'S']]": 0, "['NP', ['NP', 'VP']]": 0, "['NP', ['DT', 'NNS', 'CC', 'NNS']]": 0, "['VP', ['VBN', 'PP']]": 0, "['VP', ['MD', 'ADVP', 'VP']]": 0, "['NP', ['DT', 'NN', 'NN']]": 0, "Comparison_Arg1_Explicit": 0, "Comparison_Arg1_Implicit": 0, "Comparison_Arg2_Explicit": 0, "Comparison_Arg2_Implicit": 0, "Contingency_Arg1_Explicit": 0, "Contingency_Arg1_Implicit": 0, "Contingency_Arg2_Explicit": 0, "Contingency_Arg2_Implicit": 0, "Expansion_Arg1_Explicit": 1, "Expansion_Arg1_Implicit": 1, "Expansion_Arg2_Explicit": 0, "Expansion_Arg2_Implicit": 2, "Temporal_Arg1_Explicit": 0, "Temporal_Arg1_Implicit": 0, "Temporal_Arg2_Explicit": 0, "Temporal_Arg2_Implicit": 0, "presence_positive_associations": 1, "presence_negative_associations": 1, "ratio_positive_associations": 1.1136363636363635, "ratio_negative_associations": 0.29545454545454547, "between_forward_indicators": 0, "between_backwards_indicators": 0, "between_thesis_indicators": 0, "between_rebuttal_indicators": 0}, "4,5": {"is_a_relation": 0, "num_tokens": 58, "same_sentence": 0, "target_before_source": 0, "intro_or_conc": 0, "num_between": 0, "num_in_paragraph": 3, "share_noun": 1, "num_shared_nouns": 2, "first_or_last": 1, "component_forward_indicators": 1, "context_forward_indicators": 0, "component_backwards_indicators": 0, "context_backwards_indicators": 0, "component_thesis_indicators": 0, "context_thesis_indicators": 0, "component_rebuttal_indicators": 0, "context_rebuttal_indicators": 0, "CC": 3, "CD": 0, "DT": 6, "EX": 0, "FW": 0, "IN": 10, "JJ": 6, "JJR": 1, "JJS": 0, "LS": 0, "MD": 2, "NN": 9, "NNS": 7, "NNP": 0, "NNPS": 0, "PDT": 0, "POS": 0, "PRP": 2, "PRP$": 1, "RB": 0, "RBR": 0, "RBS": 0, "RP": 0, "SYM": 0, "TO": 1, "UH": 0, "VB": 3, "VBD": 0, "VBG": 2, "VBN": 2, "VBP": 1, "VBZ": 1, "WDT": 0, "WP": 0, "WP$": 0, "WRB": 0, "['PP', ['IN', 'NP']]": 4, "['NP', ['NP', 'PP']]": 1, "['NP', ['NN']]": 1, "['NP', ['DT', 'NN']]": 2, "['S', ['VP']]": 2, "['NP', ['NNS']]": 1, "['ROOT', ['S']]": 1, "['NP', ['PRP']]": 1, "['NP', ['JJ', 'NN']]": 0, "['NP', ['DT', 'NNS']]": 0, "['S', ['NP', 'VP']]": 1, "['ADVP', ['RB']]": 0, "['NP', ['DT', 'JJ', 'NN']]": 0, "['VP', ['VBP', 'SBAR']]": 0, "['SBAR', ['IN', 'S']]": 0, "['NP', ['JJ', 'NNS']]": 0, "['NP', ['NP', 'SBAR']]": 0, "['SBAR', ['WHNP', 'S']]": 0, "['S', ['NP', 'VP', '.']]": 0, "['VP', ['TO', 'VP']]": 0, "['VP', ['VB', 'NP', 'PP', 'PP']]": 0, "['NP', ['PRP$', 'NN']]": 0, "['VP', ['VBG', 'NP']]": 0, "['VP', ['MD', 'VP']]": 1, "['VP', ['VB', 'NP', 'PP']]": 1, "['S', ['PP', ',', 'NP', 'VP', '.']]": 0, "['ROOT', ['FRAG']]": 0, "['FRAG', ['ADVP', ',', 'NP', 'PP', '.']]": 0, "['NP', ['NN', 'NN', 'NN']]": 0, "['NP', ['NN', 'NNS']]": 0, "['PP', ['IN', 'IN', 'NP']]": 0, "['WHNP', ['WDT']]": 0, "['VP', ['VBZ', 'NP']]": 0, "['VP', ['VBP', 'S']]": 0, "['NP', ['ADJP', 'NNS']]": 0, "['ADJP', ['JJ', 'CC', 'JJ']]": 0, "['VP', ['VP', 'CC', 'VP']]": 0, "['VP', ['VBD', 'NP', 'PP']]": 0, "['NP', ['PRP$', 'VBN', 'NN']]": 0, "['VP', ['VB', 'S']]": 0, "['S', ['NP', 'ADJP']]": 0, "['ADJP', ['JJ', 'PP']]": 0, "['S', ['NP', ',', 'VP', '.']]": 0, "['NP', ['DT']]": 0, "['WHNP', ['WP']]": 0, "['VP', ['VBP']]": 0, "['VP', ['VBP', 'ADVP', 'PP']]": 0, "['S', ['S', 'CC', 'S', '.']]": 0, "['S', ['S', ',', 'NP', 'VP']]": 0, "['NP', ['JJR', 'NN']]": 0, "['NP', ['JJ', 'JJ', 'NNS']]": 0, "['VP', ['VBZ', 'PP']]": 0, "['PP', ['IN', 'S']]": 0, "['NP', ['NP', 'PP', 'PP']]": 0, "['NP', ['UCP', 'NNS']]": 0, "['UCP', ['JJ', 'CC', 'JJ']]": 0, "['VP', ['VB', 'VP']]": 0, "['VP', ['VBN', 'NP', 'PP', 'S']]": 0, "['NP', ['NP', 'VP']]": 0, "['NP', ['DT', 'NNS', 'CC', 'NNS']]": 0, "['VP', ['VBN', 'PP']]": 0, "['VP', ['MD', 'ADVP', 'VP']]": 0, "['NP', ['DT', 'NN', 'NN']]": 0, "Comparison_Arg1_Explicit": 0, "Comparison_Arg1_Implicit": 0, "Comparison_Arg2_Explicit": 0, "Comparison_Arg2_Implicit": 0, "Contingency_Arg1_Explicit": 0, "Contingency_Arg1_Implicit": 0, "Contingency_Arg2_Explicit": 0, "Contingency_Arg2_Implicit": 0, "Expansion_Arg1_Explicit": 2, "Expansion_Arg1_Implicit": 0, "Expansion_Arg2_Explicit": 1, "Expansion_Arg2_Implicit": 1, "Temporal_Arg1_Explicit": 0, "Temporal_Arg1_Implicit": 0, "Temporal_Arg2_Explicit": 0, "Temporal_Arg2_Implicit": 0, "presence_positive_associations": 1, "presence_negative_associations": 1, "ratio_positive_associations": 0.8448275862068966, "ratio_negative_associations": 0.22413793103448276, "between_forward_indicators": 0, "between_backwards_indicators": 0, "between_thesis_indicators": 0, "between_rebuttal_indicators": 0}, "5,3": {"is_a_relation": 1, "num_tokens": 40, "same_sentence": 0, "target_before_source": 1, "intro_or_conc": 0, "num_between": 1, "num_in_paragraph": 3, "share_noun": 1, "num_shared_nouns": 1, "first_or_last": 1, "component_forward_indicators": 0, "context_forward_indicators": 0, "component_backwards_indicators": 0, "context_backwards_indicators": 0, "component_thesis_indicators": 0, "context_thesis_indicators": 0, "component_rebuttal_indicators": 1, "context_rebuttal_indicators": 0, "CC": 1, "CD": 0, "DT": 5, "EX": 0, "FW": 0, "IN": 8, "JJ": 3, "JJR": 0, "JJS": 0, "LS": 0, "MD": 1, "NN": 7, "NNS": 5, "NNP": 0, "NNPS": 0, "PDT": 0, "POS": 0, "PRP": 1, "PRP$": 1, "RB": 1, "RBR": 0, "RBS": 0, "RP": 0, "SYM": 0, "TO": 1, "UH": 0, "VB": 2, "VBD": 0, "VBG": 0, "VBN": 2, "VBP": 2, "VBZ": 0, "WDT": 0, "WP": 0, "WP$": 0, "WRB": 0, "['PP', ['IN', 'NP']]": 5, "['NP', ['NP', 'PP']]": 1, "['NP', ['NN']]": 2, "['NP', ['DT', 'NN']]": 2, "['S', ['VP']]": 1, "['NP', ['NNS']]": 0, "['ROOT', ['S']]": 1, "['NP', ['PRP']]": 0, "['NP', ['JJ', 'NN']]": 0, "['NP', ['DT', 'NNS']]": 0, "['S', ['NP', 'VP']]": 1, "['ADVP', ['RB']]": 0, "['NP', ['DT', 'JJ', 'NN']]": 0, "['VP', ['VBP', 'SBAR']]": 1, "['SBAR', ['IN', 'S']]": 1, "['NP', ['JJ', 'NNS']]": 1, "['NP', ['NP', 'SBAR']]": 0, "['SBAR', ['WHNP', 'S']]": 0, "['S', ['NP', 'VP', '.']]": 0, "['VP', ['TO', 'VP']]": 0, "['VP', ['VB', 'NP', 'PP', 'PP']]": 0, "['NP', ['PRP$', 'NN']]": 0, "['VP', ['VBG', 'NP']]": 0, "['VP', ['MD', 'VP']]": 0, "['VP', ['VB', 'NP', 'PP']]": 0, "['S', ['PP', ',', 'NP', 'VP', '.']]": 0, "['ROOT', ['FRAG']]": 0, "['FRAG', ['ADVP', ',', 'NP', 'PP', '.']]": 0, "['NP', ['NN', 'NN', 'NN']]": 0, "['NP', ['NN', 'NNS']]": 0, "['PP', ['IN', 'IN', 'NP']]": 0, "['WHNP', ['WDT']]": 0, "['VP', ['VBZ', 'NP']]": 0, "['VP', ['VBP', 'S']]": 0, "['NP', ['ADJP', 'NNS']]": 0, "['ADJP', ['JJ', 'CC', 'JJ']]": 0, "['VP', ['VP', 'CC', 'VP']]": 0, "['VP', ['VBD', 'NP', 'PP']]": 0, "['NP', ['PRP$', 'VBN', 'NN']]": 0, "['VP', ['VB', 'S']]": 0, "['S', ['NP', 'ADJP']]": 0, "['ADJP', ['JJ', 'PP']]": 0, "['S', ['NP', ',', 'VP', '.']]": 0, "['NP', ['DT']]": 0, "['WHNP', ['WP']]": 0, "['VP', ['VBP']]": 0, "['VP', ['VBP', 'ADVP', 'PP']]": 0, "['S', ['S', 'CC', 'S', '.']]": 0, "['S', ['S', ',', 'NP', 'VP']]": 0, "['NP', ['JJR', 'NN']]": 0, "['NP', ['JJ', 'JJ', 'NNS']]": 0, "['VP', ['VBZ', 'PP']]": 0, "['PP', ['IN', 'S']]": 0, "['NP', ['NP', 'PP', 'PP']]": 0, "['NP', ['UCP', 'NNS']]": 0, "['UCP', ['JJ', 'CC', 'JJ']]": 0, "['VP', ['VB', 'VP']]": 0, "['VP', ['VBN', 'NP', 'PP', 'S']]": 0, "['NP', ['NP', 'VP']]": 0, "['NP', ['DT', 'NNS', 'CC', 'NNS']]": 0, "['VP', ['VBN', 'PP']]": 0, "['VP', ['MD', 'ADVP', 'VP']]": 0, "['NP', ['DT', 'NN', 'NN']]": 0, "Comparison_Arg1_Explicit": 0, "Comparison_Arg1_Implicit": 0, "Comparison_Arg2_Explicit": 0, "Comparison_Arg2_Implicit": 0, "Contingency_Arg1_Explicit": 0, "Contingency_Arg1_Implicit": 0, "Contingency_Arg2_Explicit": 0, "Contingency_Arg2_Implicit": 0, "Expansion_Arg1_Explicit": 1, "Expansion_Arg1_Implicit": 1, "Expansion_Arg2_Explicit": 1, "Expansion_Arg2_Implicit": 1, "Temporal_Arg1_Explicit": 0, "Temporal_Arg1_Implicit": 0, "Temporal_Arg2_Explicit": 0, "Temporal_Arg2_Implicit": 0, "presence_positive_associations": 1, "presence_negative_associations": 1, "ratio_positive_associations": 1.1, "ratio_negative_associations": 0.225, "between_forward_indicators": 1, "between_backwards_indicators": 0, "between_thesis_indicators": 0, "between_rebuttal_indicators": 0}, "5,4": {"is_a_relation": 0, "num_tokens": 58, "same_sentence": 0, "target_before_source": 1, "intro_or_conc": 0, "num_between": 0, "num_in_paragraph": 3, "share_noun": 1, "num_shared_nouns": 2, "first_or_last": 1, "component_forward_indicators": 1, "context_forward_indicators": 0, "component_backwards_indicators": 0, "context_backwards_indicators": 0, "component_thesis_indicators": 0, "context_thesis_indicators": 0, "component_rebuttal_indicators": 0, "context_rebuttal_indicators": 0, "CC": 3, "CD": 0, "DT": 6, "EX": 0, "FW": 0, "IN": 10, "JJ": 6, "JJR": 1, "JJS": 0, "LS": 0, "MD": 2, "NN": 9, "NNS": 7, "NNP": 0, "NNPS": 0, "PDT": 0, "POS": 0, "PRP": 2, "PRP$": 1, "RB": 0, "RBR": 0, "RBS": 0, "RP": 0, "SYM": 0, "TO": 1, "UH": 0, "VB": 3, "VBD": 0, "VBG": 2, "VBN": 2, "VBP": 1, "VBZ": 1, "WDT": 0, "WP": 0, "WP$": 0, "WRB": 0, "['PP', ['IN', 'NP']]": 5, "['NP', ['NP', 'PP']]": 1, "['NP', ['NN']]": 2, "['NP', ['DT', 'NN']]": 2, "['S', ['VP']]": 1, "['NP', ['NNS']]": 1, "['ROOT', ['S']]": 1, "['NP', ['PRP']]": 1, "['NP', ['JJ', 'NN']]": 0, "['NP', ['DT', 'NNS']]": 0, "['S', ['NP', 'VP']]": 1, "['ADVP', ['RB']]": 0, "['NP', ['DT', 'JJ', 'NN']]": 0, "['VP', ['VBP', 'SBAR']]": 0, "['SBAR', ['IN', 'S']]": 0, "['NP', ['JJ', 'NNS']]": 0, "['NP', ['NP', 'SBAR']]": 0, "['SBAR', ['WHNP', 'S']]": 0, "['S', ['NP', 'VP', '.']]": 0, "['VP', ['TO', 'VP']]": 0, "['VP', ['VB', 'NP', 'PP', 'PP']]": 0, "['NP', ['PRP$', 'NN']]": 0, "['VP', ['VBG', 'NP']]": 0, "['VP', ['MD', 'VP']]": 1, "['VP', ['VB', 'NP', 'PP']]": 1, "['S', ['PP', ',', 'NP', 'VP', '.']]": 0, "['ROOT', ['FRAG']]": 0, "['FRAG', ['ADVP', ',', 'NP', 'PP', '.']]": 0, "['NP', ['NN', 'NN', 'NN']]": 0, "['NP', ['NN', 'NNS']]": 0, "['PP', ['IN', 'IN', 'NP']]": 0, "['WHNP', ['WDT']]": 0, "['VP', ['VBZ', 'NP']]": 0, "['VP', ['VBP', 'S']]": 0, "['NP', ['ADJP', 'NNS']]": 0, "['ADJP', ['JJ', 'CC', 'JJ']]": 0, "['VP', ['VP', 'CC', 'VP']]": 0, "['VP', ['VBD', 'NP', 'PP']]": 0, "['NP', ['PRP$', 'VBN', 'NN']]": 0, "['VP', ['VB', 'S']]": 0, "['S', ['NP', 'ADJP']]": 0, "['ADJP', ['JJ', 'PP']]": 0, "['S', ['NP', ',', 'VP', '.']]": 0, "['NP', ['DT']]": 0, "['WHNP', ['WP']]": 0, "['VP', ['VBP']]": 0, "['VP', ['VBP', 'ADVP', 'PP']]": 0, "['S', ['S', 'CC', 'S', '.']]": 0, "['S', ['S', ',', 'NP', 'VP']]": 0, "['NP', ['JJR', 'NN']]": 0, "['NP', ['JJ', 'JJ', 'NNS']]": 0, "['VP', ['VBZ', 'PP']]": 0, "['PP', ['IN', 'S']]": 0, "['NP', ['NP', 'PP', 'PP']]": 0, "['NP', ['UCP', 'NNS']]": 0, "['UCP', ['JJ', 'CC', 'JJ']]": 0, "['VP', ['VB', 'VP']]": 0, "['VP', ['VBN', 'NP', 'PP', 'S']]": 0, "['NP', ['NP', 'VP']]": 0, "['NP', ['DT', 'NNS', 'CC', 'NNS']]": 0, "['VP', ['VBN', 'PP']]": 0, "['VP', ['MD', 'ADVP', 'VP']]": 0, "['NP', ['DT', 'NN', 'NN']]": 0, "Comparison_Arg1_Explicit": 0, "Comparison_Arg1_Implicit": 0, "Comparison_Arg2_Explicit": 0, "Comparison_Arg2_Implicit": 0, "Contingency_Arg1_Explicit": 0, "Contingency_Arg1_Implicit": 0, "Contingency_Arg2_Explicit": 0, "Contingency_Arg2_Implicit": 0, "Expansion_Arg1_Explicit": 2, "Expansion_Arg1_Implicit": 0, "Expansion_Arg2_Explicit": 1, "Expansion_Arg2_Implicit": 1, "Temporal_Arg1_Explicit": 0, "Temporal_Arg1_Implicit": 0, "Temporal_Arg2_Explicit": 0, "Temporal_Arg2_Implicit": 0, "presence_positive_associations": 1, "presence_negative_associations": 1, "ratio_positive_associations": 0.7586206896551724, "ratio_negative_associations": 0.15517241379310345, "between_forward_indicators": 0, "between_backwards_indicators": 0, "between_thesis_indicators": 0, "between_rebuttal_indicators": 0}, "6,7": {"is_a_relation": 0, "num_tokens": 23, "same_sentence": 1, "target_before_source": 0, "intro_or_conc": 0, "num_between": 0, "num_in_paragraph": 2, "share_noun": 1, "num_shared_nouns": 1, "first_or_last": 1, "component_forward_indicators": 0, "context_forward_indicators": 0, "component_backwards_indicators": 0, "context_backwards_indicators": 1, "component_thesis_indicators": 0, "context_thesis_indicators": 0, "component_rebuttal_indicators": 0, "context_rebuttal_indicators": 0, "CC": 0, "CD": 0, "DT": 2, "EX": 0, "FW": 0, "IN": 6, "JJ": 3, "JJR": 0, "JJS": 0, "LS": 0, "MD": 0, "NN": 7, "NNS": 3, "NNP": 0, "NNPS": 0, "PDT": 0, "POS": 0, "PRP": 0, "PRP$": 0, "RB": 0, "RBR": 0, "RBS": 0, "RP": 0, "SYM": 0, "TO": 0, "UH": 0, "VB": 0, "VBD": 0, "VBG": 0, "VBN": 0, "VBP": 0, "VBZ": 1, "WDT": 1, "WP": 0, "WP$": 0, "WRB": 0, "['PP', ['IN', 'NP']]": 8, "['NP', ['NP', 'PP']]": 8, "['NP', ['NN']]": 2, "['NP', ['DT', 'NN']]": 1, "['S', ['VP']]": 1, "['NP', ['NNS']]": 2, "['ROOT', ['S']]": 0, "['NP', ['PRP']]": 0, "['NP', ['JJ', 'NN']]": 2, "['NP', ['DT', 'NNS']]": 1, "['S', ['NP', 'VP']]": 0, "['ADVP', ['RB']]": 1, "['NP', ['DT', 'JJ', 'NN']]": 1, "['VP', ['VBP', 'SBAR']]": 0, "['SBAR', ['IN', 'S']]": 0, "['NP', ['JJ', 'NNS']]": 0, "['NP', ['NP', 'SBAR']]": 1, "['SBAR', ['WHNP', 'S']]": 1, "['S', ['NP', 'VP', '.']]": 0, "['VP', ['TO', 'VP']]": 0, "['VP', ['VB', 'NP', 'PP', 'PP']]": 0, "['NP', ['PRP$', 'NN']]": 0, "['VP', ['VBG', 'NP']]": 0, "['VP', ['MD', 'VP']]": 0, "['VP', ['VB', 'NP', 'PP']]": 0, "['S', ['PP', ',', 'NP', 'VP', '.']]": 0, "['ROOT', ['FRAG']]": 1, "['FRAG', ['ADVP', ',', 'NP', 'PP', '.']]": 1, "['NP', ['NN', 'NN', 'NN']]": 1, "['NP', ['NN', 'NNS']]": 1, "['PP', ['IN', 'IN', 'NP']]": 1, "['WHNP', ['WDT']]": 1, "['VP', ['VBZ', 'NP']]": 1, "['VP', ['VBP', 'S']]": 0, "['NP', ['ADJP', 'NNS']]": 0, "['ADJP', ['JJ', 'CC', 'JJ']]": 0, "['VP', ['VP', 'CC', 'VP']]": 0, "['VP', ['VBD', 'NP', 'PP']]": 0, "['NP', ['PRP$', 'VBN', 'NN']]": 0, "['VP', ['VB', 'S']]": 0, "['S', ['NP', 'ADJP']]": 0, "['ADJP', ['JJ', 'PP']]": 0, "['S', ['NP', ',', 'VP', '.']]": 0, "['NP', ['DT']]": 0, "['WHNP', ['WP']]": 0, "['VP', ['VBP']]": 0, "['VP', ['VBP', 'ADVP', 'PP']]": 0, "['S', ['S', 'CC', 'S', '.']]": 0, "['S', ['S', ',', 'NP', 'VP']]": 0, "['NP', ['JJR', 'NN']]": 0, "['NP', ['JJ', 'JJ', 'NNS']]": 0, "['VP', ['VBZ', 'PP']]": 0, "['PP', ['IN', 'S']]": 0, "['NP', ['NP', 'PP', 'PP']]": 0, "['NP', ['UCP', 'NNS']]": 0, "['UCP', ['JJ', 'CC', 'JJ']]": 0, "['VP', ['VB', 'VP']]": 0, "['VP', ['VBN', 'NP', 'PP', 'S']]": 0, "['NP', ['NP', 'VP']]": 0, "['NP', ['DT', 'NNS', 'CC', 'NNS']]": 0, "['VP', ['VBN', 'PP']]": 0, "['VP', ['MD', 'ADVP', 'VP']]": 0, "['NP', ['DT', 'NN', 'NN']]": 0, "Comparison_Arg1_Explicit": 0, "Comparison_Arg1_Implicit": 0, "Comparison_Arg2_Explicit": 0, "Comparison_Arg2_Implicit": 0, "Contingency_Arg1_Explicit": 0, "Contingency_Arg1_Implicit": 0, "Contingency_Arg2_Explicit": 0, "Contingency_Arg2_Implicit": 0, "Expansion_Arg1_Explicit": 0, "Expansion_Arg1_Implicit": 0, "Expansion_Arg2_Explicit": 2, "Expansion_Arg2_Implicit": 0, "Temporal_Arg1_Explicit": 0, "Temporal_Arg1_Implicit": 0, "Temporal_Arg2_Explicit": 0, "Temporal_Arg2_Implicit": 0, "presence_positive_associations": 1, "presence_negative_associations": 1, "ratio_positive_associations": 0.6521739130434783, "ratio_negative_associations": 0.043478260869565216, "between_forward_indicators": 0, "between_backwards_indicators": 0, "between_thesis_indicators": 0, "between_rebuttal_indicators": 0}, "7,6": {"is_a_relation": 1, "num_tokens": 23, "same_sentence": 1, "target_before_source": 1, "intro_or_conc": 0, "num_between": 0, "num_in_paragraph": 2, "share_noun": 1, "num_shared_nouns": 1, "first_or_last": 1, "component_forward_indicators": 0, "context_forward_indicators": 0, "component_backwards_indicators": 0, "context_backwards_indicators": 1, "component_thesis_indicators": 0, "context_thesis_indicators": 0, "component_rebuttal_indicators": 0, "context_rebuttal_indicators": 0, "CC": 0, "CD": 0, "DT": 2, "EX": 0, "FW": 0, "IN": 6, "JJ": 3, "JJR": 0, "JJS": 0, "LS": 0, "MD": 0, "NN": 7, "NNS": 3, "NNP": 0, "NNPS": 0, "PDT": 0, "POS": 0, "PRP": 0, "PRP$": 0, "RB": 0, "RBR": 0, "RBS": 0, "RP": 0, "SYM": 0, "TO": 0, "UH": 0, "VB": 0, "VBD": 0, "VBG": 0, "VBN": 0, "VBP": 0, "VBZ": 1, "WDT": 1, "WP": 0, "WP$": 0, "WRB": 0, "['PP', ['IN', 'NP']]": 8, "['NP', ['NP', 'PP']]": 8, "['NP', ['NN']]": 2, "['NP', ['DT', 'NN']]": 1, "['S', ['VP']]": 1, "['NP', ['NNS']]": 2, "['ROOT', ['S']]": 0, "['NP', ['PRP']]": 0, "['NP', ['JJ', 'NN']]": 2, "['NP', ['DT', 'NNS']]": 1, "['S', ['NP', 'VP']]": 0, "['ADVP', ['RB']]": 1, "['NP', ['DT', 'JJ', 'NN']]": 1, "['VP', ['VBP', 'SBAR']]": 0, "['SBAR', ['IN', 'S']]": 0, "['NP', ['JJ', 'NNS']]": 0, "['NP', ['NP', 'SBAR']]": 1, "['SBAR', ['WHNP', 'S']]": 1, "['S', ['NP', 'VP', '.']]": 0, "['VP', ['TO', 'VP']]": 0, "['VP', ['VB', 'NP', 'PP', 'PP']]": 0, "['NP', ['PRP$', 'NN']]": 0, "['VP', ['VBG', 'NP']]": 0, "['VP', ['MD', 'VP']]": 0, "['VP', ['VB', 'NP', 'PP']]": 0, "['S', ['PP', ',', 'NP', 'VP', '.']]": 0, "['ROOT', ['FRAG']]": 1, "['FRAG', ['ADVP', ',', 'NP', 'PP', '.']]": 1, "['NP', ['NN', 'NN', 'NN']]": 1, "['NP', ['NN', 'NNS']]": 1, "['PP', ['IN', 'IN', 'NP']]": 1, "['WHNP', ['WDT']]": 1, "['VP', ['VBZ', 'NP']]": 1, "['VP', ['VBP', 'S']]": 0, "['NP', ['ADJP', 'NNS']]": 0, "['ADJP', ['JJ', 'CC', 'JJ']]": 0, "['VP', ['VP', 'CC', 'VP']]": 0, "['VP', ['VBD', 'NP', 'PP']]": 0, "['NP', ['PRP$', 'VBN', 'NN']]": 0, "['VP', ['VB', 'S']]": 0, "['S', ['NP', 'ADJP']]": 0, "['ADJP', ['JJ', 'PP']]": 0, "['S', ['NP', ',', 'VP', '.']]": 0, "['NP', ['DT']]": 0, "['WHNP', ['WP']]": 0, "['VP', ['VBP']]": 0, "['VP', ['VBP', 'ADVP', 'PP']]": 0, "['S', ['S', 'CC', 'S', '.']]": 0, "['S', ['S', ',', 'NP', 'VP']]": 0, "['NP', ['JJR', 'NN']]": 0, "['NP', ['JJ', 'JJ', 'NNS']]": 0, "['VP', ['VBZ', 'PP']]": 0, "['PP', ['IN', 'S']]": 0, "['NP', ['NP', 'PP', 'PP']]": 0, "['NP', ['UCP', 'NNS']]": 0, "['UCP', ['JJ', 'CC', 'JJ']]": 0, "['VP', ['VB', 'VP']]": 0, "['VP', ['VBN', 'NP', 'PP', 'S']]": 0, "['NP', ['NP', 'VP']]": 0, "['NP', ['DT', 'NNS', 'CC', 'NNS']]": 0, "['VP', ['VBN', 'PP']]": 0, "['VP', ['MD', 'ADVP', 'VP']]": 0, "['NP', ['DT', 'NN', 'NN']]": 0, "Comparison_Arg1_Explicit": 0, "Comparison_Arg1_Implicit": 0, "Comparison_Arg2_Explicit": 0, "Comparison_Arg2_Implicit": 0, "Contingency_Arg1_Explicit": 0, "Contingency_Arg1_Implicit": 0, "Contingency_Arg2_Explicit": 0, "Contingency_Arg2_Implicit": 0, "Expansion_Arg1_Explicit": 0, "Expansion_Arg1_Implicit": 0, "Expansion_Arg2_Explicit": 2, "Expansion_Arg2_Implicit": 0, "Temporal_Arg1_Explicit": 0, "Temporal_Arg1_Implicit": 0, "Temporal_Arg2_Explicit": 0, "Temporal_Arg2_Implicit": 0, "presence_positive_associations": 1, "presence_negative_associations": 1, "ratio_positive_associations": 1.0, "ratio_negative_associations": 0.2608695652173913, "between_forward_indicators": 0, "between_backwards_indicators": 0, "between_thesis_indicators": 0, "between_rebuttal_indicators": 0}}